Workbook

Sheet UI Style Guide
A1: 🎨 CARTAS MÍTICAS — UI STYLE GUIDE
A2: Projeto: Atlas Iluminado / JogoCartasRoblox | B2: Data: Julho 2026 | C2: Status: Aprovado
A4: PALETA DE CORES
A5: Background Principal | B5: #0F1419 | C5: Dark Navy (fundo escuro base de todas as telas)
A6: Background Secundário | B6: #1A2332 | C6: Navy mais claro (painéis, cards)
A7: Accent Color | B7: #FFD700 | C7: Ouro vivo (destaques, CTAs importantes)
A8: Text Primário | B8: #FFFFFF | C8: Branco (textos principais, headers)
A9: Text Secundário | B9: #B0B0B0 | C9: Cinza claro (textos menores, descrições)
A10: Text Terciário | B10: #707070 | C10: Cinza escuro (labels, hints)
A12: CORES DE RARIDADE
A13: Default | B13: #E8E8E8 | C13: Cinza prata (muito claro)
A14: Bronze | B14: #C98A4B | C14: Cobre/bronze
A15: Prata | B15: #E8ECF0 | C15: Prata/cinza prateado
A16: Ouro | B16: #FFE066 | C16: Ouro quente
A17: Platina | B17: #A5F3FC | C17: Azul-ciano/platina
A18: Lendário | B18: #FF1493 | C18: Rosa choque/magenta
A19: Mítico | B19: #9D4EDD | C19: Roxo escuro/púrpura
A20: Divino | B20: #F4D03F (com prisma) | C20: Dourado com efeito prismático (prisma: violeta, ciano, dourado, rosa)
A22: TIPOGRAFIA
A23: Font Principal (Títulos, Headers) | B23: Baloo 2 | C23: Bold, 24-32px, espaçamento 0.5px
A24: Font Secundária (Descrições) | B24: Inter | C24: Regular, 12-16px, line-height 1.5
A25: Font Pequena (Labels, UI) | B25: Inter | C25: Regular, 10-12px, weight 400
A27: COMPONENTES UI
A28: Botão Principal (CTA) | B28: Fundo #FFD700, Texto #0F1419, Border-radius 4px, Padding 12px 24px | C28: Hover: +10% brilho | Press: -10% brilho
A29: Botão Secundário | B29: Border 1px #FFD700, Fundo transparent, Texto #FFD700 | C29: Hover: Fundo 20% #FFD700 | Press: Fundo 40% #FFD700
A30: Card de Criatura | B30: Fundo #1A2332, Border 2px (cor raridade), Border-radius 8px, Shadow: 0 4px 12px rgba(0,0,0,0.5)
A31: Border de Card (por raridade) | B31: Vide "CORES DE RARIDADE" acima — aplicar borda externa de 2px
A32: Border Divino (especial) | B32: Base prata animada (#E8ECF0) com lascas pastel girando em loop (6s/volta) | C32: Lascas: violeta #9370DB, ciano #00CED1, dourado #FFD700, rosa #FF69B4
A33: Input Field | B33: Fundo #0F1419, Border 1px #707070, Texto #FFFFFF, Padding 8px | C33: Focus: Border 1px #FFD700, Box-shadow: 0 0 8px rgba(255, 215, 0, 0.3)
A34: Modal/Dialog | B34: Overlay: rgba(0, 0, 0, 0.7), Container: #1A2332, Border 1px #707070 | C34: Close button (X): top-right, 16px, hover: #FFD700
A36: LAYOUT & ESPAÇAMENTO
A37: Padding Padrão (componentes) | B37: 16px | C37: Interno dos componentes
A38: Margin entre componentes | B38: 16-24px | C38: Espaçamento externo
A39: Border-radius padrão | B39: 4-8px | C39: Cantos suavizados (não usar 0)
A40: Sombra padrão (cards) | B40: 0 4px 12px rgba(0,0,0,0.5) | C40: Profundidade sutil
A42: BREAKPOINTS & RESPONSIVIDADE
A43: Mobile (Padrão no Roblox) | B43: Layout single-column, Stack vertical, Touch targets 48px min | C43: Viewport: ~380-400px
A44: Desktop (Futura) | B44: Layout multi-column, Grid/Flex, Mouse precision targets 24px | C44: Viewport: 1200px+
A46: TELAS PRINCIPAIS (6 PROTÓTIPOS)
A47: 1. Lobby / HUD | B47: Mostra: Saldo ($/$💎), Nível, Progresso do Ladder, Botões principais, Perfil | C47: Ícones: Moeda, Diamante, Engrenagem, Perfil
A48: 2. Pack Shop (Loja) | B48: Catálogo de 62 pacotes com preço, moeda, descrição breve | C48: Filtros: Categoria (Geral, Diamante, Robux, Especial) | Ordenação: Por preço/Novo
A49: 3. Pack Opening (Abertura) | B49: Animação de abertura, revelar criatura (art + nome), ver raridade, duplicar? | C49: Transição smooth com efeito de brilho na carta
A50: 4. Álbum (Coleção) | B50: Grid 4-5 cols de todas as criaturas descobertas, filtro por clã, busca por nome | C50: Mostra: Miniatura + Nome + Raridade atual + Cópias/Progresso
A51: 5. Mochila (Inventário) | B51: Lista ou grid de criaturas (1 objeto = 1 descoberta), drag-drop para Slots Base | C51: Capacity: 200 máximo | Mostra: Clã, Raridade, Stats (ATK/DEF/HP)
A52: 6. Altar de Sacrifício | B52: Staging area pre-Renascimento, colocar 3 cartas do clã + 1 nomeada + $ threshold | C52: Botão Renascer ativa quando 3 requisitos OK. Popup de confirmação.
A54: ANIMAÇÕES & TRANSIÇÕES
A55: Card appear (entrada) | B55: 200ms fade-in + translate-up (20px) | C55: Easing: ease-out
A56: Button press | B56: 100ms scale-down (0.98), bounce back | C56: Easing: ease-in-out
A57: Border Divino rotation | B57: 6000ms (6 seg) full rotation contínuo | C57: Linear, infinite, apenas anel gira, arte estática
A58: Pack opening reveal | B58: 600ms zoom-in + fade + brilho | C58: Easing: ease-out, timing staggered
A60: ICONOGRAFIA
A61: Style | B61: Flat, monochromatic, 24-48px size, fill solid | C61: Icons: Moeda ($), Diamante (💎), Fogo (🔥), Água (💧), etc.
A62: Palette | B62: Usar cores de raridade para ícones quando aplicável (ex: ícone de Prata = #E8ECF0)

Sheet Clãs - Visão Geral
A1: Clã | B1: Elemento | C1: Cor (hex) | D1: Tipo de Vantagem Elemental
A2: Ordem Celestial | B2: Luz | C2: #F4D03F | D2: Forte contra: Véu Sombrio | Fraco contra: Constelação Arcana
A3: Véu Sombrio | B3: Sombra | C3: #5B2C6F | D3: Forte contra: Constelação Arcana | Fraco contra: Ordem Celestial
A4: Fúria Selvagem | B4: Natureza | C4: #27AE60 | D4: Forte contra: Rocha Ancestral | Fraco contra: Chama Vulcânica
A5: Abismo Glacial | B5: Gelo | C5: #AED6F1 | D5: Forte contra: Fúria Selvagem | Fraco contra: Forja Ígnea
A6: Maré Eterna | B6: Água | C6: #0E5C52 | D6: Forte contra: Forja Ígnea | Fraco contra: Tempestade Rúnica
A7: Forja Ígnea | B7: Fogo | C7: #D30D0D | D7: Forte contra: Abismo Glacial | Fraco contra: Maré Eterna
A8: Tempestade Rúnica | B8: Trovão | C8: #FF99CA | D8: Forte contra: Maré Eterna | Fraco contra: Rocha Ancestral
A9: Rocha Ancestral | B9: Terra | C9: #935116 | D9: Forte contra: Tempestade Rúnica | Fraco contra: Fúria Selvagem
A10: Areia Amaldiçoada | B10: Morte | C10: #AFA88C | D10: Forte contra: Selva Esmeralda | Fraco contra: Névoa Espectral
A11: Selva Esmeralda | B11: Veneno | C11: #147B16 | D11: Forte contra: Maré Eterna (revisado) | Fraco contra: Areia Amaldiçoada
A12: Constelação Arcana | B12: Astral | C12: #B23488 | D12: Forte contra: Véu Sombrio | Fraco contra: Ordem Celestial
... A16: Engrenagem Rúnica | B16: Tecnomancia | C16: #DBF470 | D16: Versátil — bônus contra qualquer clã com HP cheio

Sheet Criaturas - Base de Dados
A1: # | B1: Clã | C1: Elemento | D1: Criatura | E1: Origem Mitológica/Cultural | F1: Descrição breve | G1: Tier de Poder Natural (lore) | H1: Valor Semente ($/s) | I1: Ataque Base | J1: Defesa Base | K1: HP Base
A2: 1 | B2: Ordem Celestial | C2: Luz | D2: Fênix Solar | E2: Grécia/Egito | F2: Ave que renasce das cinzas com fogo dourado | G2: Bronze | H2: 10 | I2: 6 | J2: 5 | K2: 32
A3: 2 | B3: Ordem Celestial | C3: Luz | D3: Grifo Guardião | E3: Pérsia/Grécia | F3: Metade leão, metade águia, protetor de tesouros sagrados | G3: Bronze | H3: 12 | I3: 7 | J3: 6 | K3: 38
A4: 3 | B4: Ordem Celestial | C4: Luz | D4: Pégaso Radiante | E4: Grécia | F4: Cavalo alado que galopa entre nuvens | G4: Bronze | H4: 14 | I4: 8 | J4: 7 | K4: 45
A5: 4 | B5: Ordem Celestial | C5: Luz | D5: Serpente-Pluma Ancestral | E5: Mesoamérica | F5: Serpente emplumada trazida pelo vento e pela luz | G5: Bronze | H5: 16 | I5: 10 | J5: 8 | K5: 51
A6: 5 | B6: Ordem Celestial | C6: Luz | D6: Unicórnio Sagrado | E6: Europa Medieval | F6: Purifica águas envenenadas com seu chifre | G6: Prata | H6: 16 | I6: 10 | J6: 8 | K6: 51
A7: 6 | B7: Ordem Celestial | C7: Luz | D7: Roc Celestial | E7: Oriente Médio | F7: Ave colossal capaz de carregar elefantes | G7: Prata | H7: 18 | I7: 11 | J7: 9 | K7: 58
A8: 7 | B8: Ordem Celestial | C8: Luz | D8: Lamassu Dourado | E8: Mesopotâmia | F8: Touro alado de cabeça humana, guardião de portais | G8: Prata | H8: 20 | I8: 12 | J8: 10 | K8: 64
A9: 8 | B9: Ordem Celestial | C9: Luz | D9: Bennu Ancestral | E9: Egito | F9: Ave-sol ligada ao ciclo do nascer e renascer | G9: Prata | H9: 22 | I9: 13 | J9: 11 | K9: 70
A10: 9 | B10: Ordem Celestial | C10: Luz | D10: Garuda Radiante | E10: Índia/Sudeste Asiático | F10: Ave divina montaria dos deuses | G10: Ouro | H10: 24 | I10: 14 | J10: 12 | K10: 77
A11: 10 | B11: Ordem Celestial | C11: Luz | D11: Simurgh Eterno | E11: Pérsia | F11: Ave sábia guardiã da árvore da vida | G11: Ouro | H11: 26 | I11: 16 | J11: 13 | K11: 83
A12: 11 | B12: Ordem Celestial | C12: Luz | D12: Kirin Puro | E12: China/Japão | F12: Besta sagrada que só aparece em tempos de paz | G12: Ouro | H12: 28 | I12: 17 | J12: 14 | K12: 90
A13: 12 | B13: Ordem Celestial | C13: Luz | D13: Huma Abençoada | E13: Pérsia | F13: Ave que nunca pousa em terra, símbolo de boa sorte | G13: Ouro | H13: 30 | I13: 18 | J13: 15 | K13: 96
... A301: 300 | B301: Engrenagem Rúnica | C301: Tecnomancia | D301: Núcleo Rúnico Ancestral | E301: Folclore Original | F301: Fonte de energia viva que dá vida a todos os autômatos do clã | G301: Mítico | H301: 71 | I301: 43 | J301: 36 | K301: 227

Sheet Sistema de Raridade e Evolução
A1: Ordem | B1: Raridade | C1: Cópias Necessárias | D1: Cópias Acumuladas (Total) | E1: Multiplicador de Valor/Stats
A2: 0 | B2: Default | C2: 1 | D2: 1 | E2: ≈ 0.30 (teste em jogo)
A3: 1 | B3: Bronze | C3: 5 | D3: 6 | E3: 1
A4: 2 | B4: Prata | C4: 10 | D4: 16 | E4: 6
A5: 3 | B5: Ouro | C5: 15 | D5: 31 | E5: 18
A6: 4 | B6: Platina | C6: 25 | D6: 56 | E6: 50
A7: 5 | B7: Lendário | C7: 35 | D7: 91 | E7: 150
A8: 6 | B8: Mítico | C8: 50 | D8: 141 | E8: 500
A9: 7 | B9: Divino | C9: N/A (Evento exclusivo) | D9: N/A | E9: 10.000
A11: ⚠️ REGRAS
A12: Evolução automática por acúmulo: | B12: Cada cópia encontrada = +1 ponto. Ao atingir cópias necessárias, salta para próx. raridade, pontos resetam a 0.
A13: Atalho de Raridade: | B13: Pacotes Geral, Diamante, Robux, Especial/Evento sorteram raridades mais altas (exceto Bênção Diária = sempre Default).
A14: Venda de Cópias: | B14: 20% do valor de mercado. Se cópias < threshold atual, downgrade automático + reset de pontos.
A15: Divino: | B15: Sem evolução por acúmulo, sem atalho de progressão. Apenas via Pacote Divino (Evento, Robux). Raridade fixa, sem downgrade.

Sheet Matriz Completa (1800 cartas)
A1: ID | B1: Clã | C1: Elemento | D1: Criatura | E1: Raridade | F1: Valor Base ($/s, Grau 7.0) | G1: Ataque | H1: Defesa | I1: HP | J1: Duplicatas p/ Próx. Raridade | K1: Próxima Raridade | L1: Valor Máx ($/s, Grau 10.0)
A2: 1 | B2: ='Criaturas - Base de Dados'!B2 -> Ordem Celestial | C2: ='Criaturas - Base de Dados'!C2 -> Luz | D2: ='Criaturas - Base de Dados'!D2 -> Fênix Solar | E2: ='Sistema de Raridade e Evolução'!B2 -> Default | F2: =ROUND(('Criaturas - Base de Dados'!H2*'Sistema de Raridade e Evolução'!E2)*1000,2) -> #VALUE! | G2: =ROUND('Criaturas - Base de Dados'!I2*'Sistema de Raridade e Evolução'!E2,0) -> #VALUE! | H2: =ROUND('Criaturas - Base de Dados'!J2*'Sistema de Raridade e Evolução'!E2,0) -> #VALUE! | I2: =ROUND('Criaturas - Base de Dados'!K2*'Sistema de Raridade e Evolução'!E2,0) -> #VALUE! | J2: ='Sistema de Raridade e Evolução'!D2 -> 1 | K2: Prata | L2: =ROUND(F2*(2.5/1.05),2) -> #VALUE!
A3: 2 | B3: ='Criaturas - Base de Dados'!B2 -> Ordem Celestial | C3: ='Criaturas - Base de Dados'!C2 -> Luz | D3: ='Criaturas - Base de Dados'!D2 -> Fênix Solar | E3: ='Sistema de Raridade e Evolução'!B3 -> Bronze | F3: =ROUND(('Criaturas - Base de Dados'!H2*'Sistema de Raridade e Evolução'!E3)*1000,2) -> 10000 | G3: =ROUND('Criaturas - Base de Dados'!I2*'Sistema de Raridade e Evolução'!E3,0) -> 6 | H3: =ROUND('Criaturas - Base de Dados'!J2*'Sistema de Raridade e Evolução'!E3,0) -> 5 | I3: =ROUND('Criaturas - Base de Dados'!K2*'Sistema de Raridade e Evolução'!E3,0) -> 32 | J3: ='Sistema de Raridade e Evolução'!D3 -> 6 | K3: Ouro | L3: =ROUND(F3*(2.5/1.05),2) -> 23809.52
A4: 3 | B4: ='Criaturas - Base de Dados'!B2 -> Ordem Celestial | C4: ='Criaturas - Base de Dados'!C2 -> Luz | D4: ='Criaturas - Base de Dados'!D2 -> Fênix Solar | E4: ='Sistema de Raridade e Evolução'!B4 -> Prata | F4: =ROUND(('Criaturas - Base de Dados'!H2*'Sistema de Raridade e Evolução'!E4)*1000,2) -> 60000 | G4: =ROUND('Criaturas - Base de Dados'!I2*'Sistema de Raridade e Evolução'!E4,0) -> 36 | H4: =ROUND('Criaturas - Base de Dados'!J2*'Sistema de Raridade e Evolução'!E4,0) -> 30 | I4: =ROUND('Criaturas - Base de Dados'!K2*'Sistema de Raridade e Evolução'!E4,0) -> 192 | J4: ='Sistema de Raridade e Evolução'!D4 -> 16 | K4: Platina | L4: =ROUND(F4*(2.5/1.05),2) -> 142857.14
A5: 4 | B5: ='Criaturas - Base de Dados'!B2 -> Ordem Celestial | C5: ='Criaturas - Base de Dados'!C2 -> Luz | D5: ='Criaturas - Base de Dados'!D2 -> Fênix Solar | E5: ='Sistema de Raridade e Evolução'!B5 -> Ouro | F5: =ROUND(('Criaturas - Base de Dados'!H2*'Sistema de Raridade e Evolução'!E5)*1000,2) -> 180000 | G5: =ROUND('Criaturas - Base de Dados'!I2*'Sistema de Raridade e Evolução'!E5,0) -> 108 | H5: =ROUND('Criaturas - Base de Dados'!J2*'Sistema de Raridade e Evolução'!E5,0) -> 90 | I5: =ROUND('Criaturas - Base de Dados'!K2*'Sistema de Raridade e Evolução'!E5,0) -> 576 | J5: ='Sistema de Raridade e Evolução'!D5 -> 31 | K5: Lendário | L5: =ROUND(F5*(2.5/1.05),2) -> 428571.43
A6: 5 | B6: ='Criaturas - Base de Dados'!B2 -> Ordem Celestial | C6: ='Criaturas - Base de Dados'!C2 -> Luz | D6: ='Criaturas - Base de Dados'!D2 -> Fênix Solar | E6: ='Sistema de Raridade e Evolução'!B6 -> Platina | F6: =ROUND(('Criaturas - Base de Dados'!H2*'Sistema de Raridade e Evolução'!E6)*1000,2) -> 500000 | G6: =ROUND('Criaturas - Base de Dados'!I2*'Sistema de Raridade e Evolução'!E6,0) -> 300 | H6: =ROUND('Criaturas - Base de Dados'!J2*'Sistema de Raridade e Evolução'!E6,0) -> 250 | I6: =ROUND('Criaturas - Base de Dados'!K2*'Sistema de Raridade e Evolução'!E6,0) -> 1600 | J6: ='Sistema de Raridade e Evolução'!D6 -> 56 | K6: Mítico | L6: =ROUND(F6*(2.5/1.05),2) -> 1190476.2
A7: 6 | B7: ='Criaturas - Base de Dados'!B2 -> Ordem Celestial | C7: ='Criaturas - Base de Dados'!C2 -> Luz | D7: ='Criaturas - Base de Dados'!D2 -> Fênix Solar | E7: ='Sistema de Raridade e Evolução'!B7 -> Lendário | F7: =ROUND(('Criaturas - Base de Dados'!H2*'Sistema de Raridade e Evolução'!E7)*1000,2) -> 1500000 | G7: =ROUND('Criaturas - Base de Dados'!I2*'Sistema de Raridade e Evolução'!E7,0) -> 900 | H7: =ROUND('Criaturas - Base de Dados'!J2*'Sistema de Raridade e Evolução'!E7,0) -> 750 | I7: =ROUND('Criaturas - Base de Dados'!K2*'Sistema de Raridade e Evolução'!E7,0) -> 4800 | J7: ='Sistema de Raridade e Evolução'!D7 -> 91 | K7: MÁXIMO | L7: =ROUND(F7*(2.5/1.05),2) -> 3571428.6
A8: 7 | B8: ='Criaturas - Base de Dados'!B3 -> Ordem Celestial | C8: ='Criaturas - Base de Dados'!C3 -> Luz | D8: ='Criaturas - Base de Dados'!D3 -> Grifo Guardião | E8: ='Sistema de Raridade e Evolução'!B2 -> Default | F8: =ROUND(('Criaturas - Base de Dados'!H3*'Sistema de Raridade e Evolução'!E2)*1000,2) -> #VALUE! | G8: =ROUND('Criaturas - Base de Dados'!I3*'Sistema de Raridade e Evolução'!E2,0) -> #VALUE! | H8: =ROUND('Criaturas - Base de Dados'!J3*'Sistema de Raridade e Evolução'!E2,0) -> #VALUE! | I8: =ROUND('Criaturas - Base de Dados'!K3*'Sistema de Raridade e Evolução'!E2,0) -> #VALUE! | J8: ='Sistema de Raridade e Evolução'!D2 -> 1 | K8: Prata | L8: =ROUND(F8*(2.5/1.05),2) -> #VALUE!
A9: 8 | B9: ='Criaturas - Base de Dados'!B3 -> Ordem Celestial | C9: ='Criaturas - Base de Dados'!C3 -> Luz | D9: ='Criaturas - Base de Dados'!D3 -> Grifo Guardião | E9: ='Sistema de Raridade e Evolução'!B3 -> Bronze | F9: =ROUND(('Criaturas - Base de Dados'!H3*'Sistema de Raridade e Evolução'!E3)*1000,2) -> 12000 | G9: =ROUND('Criaturas - Base de Dados'!I3*'Sistema de Raridade e Evolução'!E3,0) -> 7 | H9: =ROUND('Criaturas - Base de Dados'!J3*'Sistema de Raridade e Evolução'!E3,0) -> 6 | I9: =ROUND('Criaturas - Base de Dados'!K3*'Sistema de Raridade e Evolução'!E3,0) -> 38 | J9: ='Sistema de Raridade e Evolução'!D3 -> 6 | K9: Ouro | L9: =ROUND(F9*(2.5/1.05),2) -> 28571.43
A10: 9 | B10: ='Criaturas - Base de Dados'!B3 -> Ordem Celestial | C10: ='Criaturas - Base de Dados'!C3 -> Luz | D10: ='Criaturas - Base de Dados'!D3 -> Grifo Guardião | E10: ='Sistema de Raridade e Evolução'!B4 -> Prata | F10: =ROUND(('Criaturas - Base de Dados'!H3*'Sistema de Raridade e Evolução'!E4)*1000,2) -> 72000 | G10: =ROUND('Criaturas - Base de Dados'!I3*'Sistema de Raridade e Evolução'!E4,0) -> 42 | H10: =ROUND('Criaturas - Base de Dados'!J3*'Sistema de Raridade e Evolução'!E4,0) -> 36 | I10: =ROUND('Criaturas - Base de Dados'!K3*'Sistema de Raridade e Evolução'!E4,0) -> 228 | J10: ='Sistema de Raridade e Evolução'!D4 -> 16 | K10: Platina | L10: =ROUND(F10*(2.5/1.05),2) -> 171428.57
A11: 10 | B11: ='Criaturas - Base de Dados'!B3 -> Ordem Celestial | C11: ='Criaturas - Base de Dados'!C3 -> Luz | D11: ='Criaturas - Base de Dados'!D3 -> Grifo Guardião | E11: ='Sistema de Raridade e Evolução'!B5 -> Ouro | F11: =ROUND(('Criaturas - Base de Dados'!H3*'Sistema de Raridade e Evolução'!E5)*1000,2) -> 216000 | G11: =ROUND('Criaturas - Base de Dados'!I3*'Sistema de Raridade e Evolução'!E5,0) -> 126 | H11: =ROUND('Criaturas - Base de Dados'!J3*'Sistema de Raridade e Evolução'!E5,0) -> 108 | I11: =ROUND('Criaturas - Base de Dados'!K3*'Sistema de Raridade e Evolução'!E5,0) -> 684 | J11: ='Sistema de Raridade e Evolução'!D5 -> 31 | K11: Lendário | L11: =ROUND(F11*(2.5/1.05),2) -> 514285.71
A12: 11 | B12: ='Criaturas - Base de Dados'!B3 -> Ordem Celestial | C12: ='Criaturas - Base de Dados'!C3 -> Luz | D12: ='Criaturas - Base de Dados'!D3 -> Grifo Guardião | E12: ='Sistema de Raridade e Evolução'!B6 -> Platina | F12: =ROUND(('Criaturas - Base de Dados'!H3*'Sistema de Raridade e Evolução'!E6)*1000,2) -> 600000 | G12: =ROUND('Criaturas - Base de Dados'!I3*'Sistema de Raridade e Evolução'!E6,0) -> 350 | H12: =ROUND('Criaturas - Base de Dados'!J3*'Sistema de Raridade e Evolução'!E6,0) -> 300 | I12: =ROUND('Criaturas - Base de Dados'!K3*'Sistema de Raridade e Evolução'!E6,0) -> 1900 | J12: ='Sistema de Raridade e Evolução'!D6 -> 56 | K12: Mítico | L12: =ROUND(F12*(2.5/1.05),2) -> 1428571.4
A13: 12 | B13: ='Criaturas - Base de Dados'!B3 -> Ordem Celestial | C13: ='Criaturas - Base de Dados'!C3 -> Luz | D13: ='Criaturas - Base de Dados'!D3 -> Grifo Guardião | E13: ='Sistema de Raridade e Evolução'!B7 -> Lendário | F13: =ROUND(('Criaturas - Base de Dados'!H3*'Sistema de Raridade e Evolução'!E7)*1000,2) -> 1800000 | G13: =ROUND('Criaturas - Base de Dados'!I3*'Sistema de Raridade e Evolução'!E7,0) -> 1050 | H13: =ROUND('Criaturas - Base de Dados'!J3*'Sistema de Raridade e Evolução'!E7,0) -> 900 | I13: =ROUND('Criaturas - Base de Dados'!K3*'Sistema de Raridade e Evolução'!E7,0) -> 5700 | J13: ='Sistema de Raridade e Evolução'!D7 -> 91 | K13: MÁXIMO | L13: =ROUND(F13*(2.5/1.05),2) -> 4285714.3
A14: 13 | B14: ='Criaturas - Base de Dados'!B4 -> Ordem Celestial | C14: ='Criaturas - Base de Dados'!C4 -> Luz | D14: ='Criaturas - Base de Dados'!D4 -> Pégaso Radiante | E14: ='Sistema de Raridade e Evolução'!B2 -> Default | F14: =ROUND(('Criaturas - Base de Dados'!H4*'Sistema de Raridade e Evolução'!E2)*1000,2) -> #VALUE! | G14: =ROUND('Criaturas - Base de Dados'!I4*'Sistema de Raridade e Evolução'!E2,0) -> #VALUE! | H14: =ROUND('Criaturas - Base de Dados'!J4*'Sistema de Raridade e Evolução'!E2,0) -> #VALUE! | I14: =ROUND('Criaturas - Base de Dados'!K4*'Sistema de Raridade e Evolução'!E2,0) -> #VALUE! | J14: ='Sistema de Raridade e Evolução'!D2 -> 1 | K14: Prata | L14: =ROUND(F14*(2.5/1.05),2) -> #VALUE!
A15: 14 | B15: ='Criaturas - Base de Dados'!B4 -> Ordem Celestial | C15: ='Criaturas - Base de Dados'!C4 -> Luz | D15: ='Criaturas - Base de Dados'!D4 -> Pégaso Radiante | E15: ='Sistema de Raridade e Evolução'!B3 -> Bronze | F15: =ROUND(('Criaturas - Base de Dados'!H4*'Sistema de Raridade e Evolução'!E3)*1000,2) -> 14000 | G15: =ROUND('Criaturas - Base de Dados'!I4*'Sistema de Raridade e Evolução'!E3,0) -> 8 | H15: =ROUND('Criaturas - Base de Dados'!J4*'Sistema de Raridade e Evolução'!E3,0) -> 7 | I15: =ROUND('Criaturas - Base de Dados'!K4*'Sistema de Raridade e Evolução'!E3,0) -> 45 | J15: ='Sistema de Raridade e Evolução'!D3 -> 6 | K15: Ouro | L15: =ROUND(F15*(2.5/1.05),2) -> 33333.33
A16: 15 | B16: ='Criaturas - Base de Dados'!B4 -> Ordem Celestial | C16: ='Criaturas - Base de Dados'!C4 -> Luz | D16: ='Criaturas - Base de Dados'!D4 -> Pégaso Radiante | E16: ='Sistema de Raridade e Evolução'!B4 -> Prata | F16: =ROUND(('Criaturas - Base de Dados'!H4*'Sistema de Raridade e Evolução'!E4)*1000,2) -> 84000 | G16: =ROUND('Criaturas - Base de Dados'!I4*'Sistema de Raridade e Evolução'!E4,0) -> 48 | H16: =ROUND('Criaturas - Base de Dados'!J4*'Sistema de Raridade e Evolução'!E4,0) -> 42 | I16: =ROUND('Criaturas - Base de Dados'!K4*'Sistema de Raridade e Evolução'!E4,0) -> 270 | J16: ='Sistema de Raridade e Evolução'!D4 -> 16 | K16: Platina | L16: =ROUND(F16*(2.5/1.05),2) -> 200000
A17: 16 | B17: ='Criaturas - Base de Dados'!B4 -> Ordem Celestial | C17: ='Criaturas - Base de Dados'!C4 -> Luz | D17: ='Criaturas - Base de Dados'!D4 -> Pégaso Radiante | E17: ='Sistema de Raridade e Evolução'!B5 -> Ouro | F17: =ROUND(('Criaturas - Base de Dados'!H4*'Sistema de Raridade e Evolução'!E5)*1000,2) -> 252000 | G17: =ROUND('Criaturas - Base de Dados'!I4*'Sistema de Raridade e Evolução'!E5,0) -> 144 | H17: =ROUND('Criaturas - Base de Dados'!J4*'Sistema de Raridade e Evolução'!E5,0) -> 126 | I17: =ROUND('Criaturas - Base de Dados'!K4*'Sistema de Raridade e Evolução'!E5,0) -> 810 | J17: ='Sistema de Raridade e Evolução'!D5 -> 31 | K17: Lendário | L17: =ROUND(F17*(2.5/1.05),2) -> 600000
A18: 17 | B18: ='Criaturas - Base de Dados'!B4 -> Ordem Celestial | C18: ='Criaturas - Base de Dados'!C4 -> Luz | D18: ='Criaturas - Base de Dados'!D4 -> Pégaso Radiante | E18: ='Sistema de Raridade e Evolução'!B6 -> Platina | F18: =ROUND(('Criaturas - Base de Dados'!H4*'Sistema de Raridade e Evolução'!E6)*1000,2) -> 700000 | G18: =ROUND('Criaturas - Base de Dados'!I4*'Sistema de Raridade e Evolução'!E6,0) -> 400 | H18: =ROUND('Criaturas - Base de Dados'!J4*'Sistema de Raridade e Evolução'!E6,0) -> 350 | I18: =ROUND('Criaturas - Base de Dados'!K4*'Sistema de Raridade e Evolução'!E6,0) -> 2250 | J18: ='Sistema de Raridade e Evolução'!D6 -> 56 | K18: Mítico | L18: =ROUND(F18*(2.5/1.05),2) -> 1666666.7
A19: 18 | B19: ='Criaturas - Base de Dados'!B4 -> Ordem Celestial | C19: ='Criaturas - Base de Dados'!C4 -> Luz | D19: ='Criaturas - Base de Dados'!D4 -> Pégaso Radiante | E19: ='Sistema de Raridade e Evolução'!B7 -> Lendário | F19: =ROUND(('Criaturas - Base de Dados'!H4*'Sistema de Raridade e Evolução'!E7)*1000,2) -> 2100000 | G19: =ROUND('Criaturas - Base de Dados'!I4*'Sistema de Raridade e Evolução'!E7,0) -> 1200 | H19: =ROUND('Criaturas - Base de Dados'!J4*'Sistema de Raridade e Evolução'!E7,0) -> 1050 | I19: =ROUND('Criaturas - Base de Dados'!K4*'Sistema de Raridade e Evolução'!E7,0) -> 6750 | J19: ='Sistema de Raridade e Evolução'!D7 -> 91 | K19: MÁXIMO | L19: =ROUND(F19*(2.5/1.05),2) -> 5000000
A20: 19 | B20: ='Criaturas - Base de Dados'!B5 -> Ordem Celestial | C20: ='Criaturas - Base de Dados'!C5 -> Luz | D20: ='Criaturas - Base de Dados'!D5 -> Serpente-Pluma Ancestral | E20: ='Sistema de Raridade e Evolução'!B2 -> Default | F20: =ROUND(('Criaturas - Base de Dados'!H5*'Sistema de Raridade e Evolução'!E2)*1000,2) -> #VALUE! | G20: =ROUND('Criaturas - Base de Dados'!I5*'Sistema de Raridade e Evolução'!E2,0) -> #VALUE! | H20: =ROUND('Criaturas - Base de Dados'!J5*'Sistema de Raridade e Evolução'!E2,0) -> #VALUE! | I20: =ROUND('Criaturas - Base de Dados'!K5*'Sistema de Raridade e Evolução'!E2,0) -> #VALUE! | J20: ='Sistema de Raridade e Evolução'!D2 -> 1 | K20: Prata | L20: =ROUND(F20*(2.5/1.05),2) -> #VALUE!
A21: 20 | B21: ='Criaturas - Base de Dados'!B5 -> Ordem Celestial | C21: ='Criaturas - Base de Dados'!C5 -> Luz | D21: ='Criaturas - Base de Dados'!D5 -> Serpente-Pluma Ancestral | E21: ='Sistema de Raridade e Evolução'!B3 -> Bronze | F21: =ROUND(('Criaturas - Base de Dados'!H5*'Sistema de Raridade e Evolução'!E3)*1000,2) -> 16000 | G21: =ROUND('Criaturas - Base de Dados'!I5*'Sistema de Raridade e Evolução'!E3,0) -> 10 | H21: =ROUND('Criaturas - Base de Dados'!J5*'Sistema de Raridade e Evolução'!E3,0) -> 8 | I21: =ROUND('Criaturas - Base de Dados'!K5*'Sistema de Raridade e Evolução'!E3,0) -> 51 | J21: ='Sistema de Raridade e Evolução'!D3 -> 6 | K21: Ouro | L21: =ROUND(F21*(2.5/1.05),2) -> 38095.24
A22: 21 | B22: ='Criaturas - Base de Dados'!B5 -> Ordem Celestial | C22: ='Criaturas - Base de Dados'!C5 -> Luz | D22: ='Criaturas - Base de Dados'!D5 -> Serpente-Pluma Ancestral | E22: ='Sistema de Raridade e Evolução'!B4 -> Prata | F22: =ROUND(('Criaturas - Base de Dados'!H5*'Sistema de Raridade e Evolução'!E4)*1000,2) -> 96000 | G22: =ROUND('Criaturas - Base de Dados'!I5*'Sistema de Raridade e Evolução'!E4,0) -> 60 | H22: =ROUND('Criaturas - Base de Dados'!J5*'Sistema de Raridade e Evolução'!E4,0) -> 48 | I22: =ROUND('Criaturas - Base de Dados'!K5*'Sistema de Raridade e Evolução'!E4,0) -> 306 | J22: ='Sistema de Raridade e Evolução'!D4 -> 16 | K22: Platina | L22: =ROUND(F22*(2.5/1.05),2) -> 228571.43
A23: 22 | B23: ='Criaturas - Base de Dados'!B5 -> Ordem Celestial | C23: ='Criaturas - Base de Dados'!C5 -> Luz | D23: ='Criaturas - Base de Dados'!D5 -> Serpente-Pluma Ancestral | E23: ='Sistema de Raridade e Evolução'!B5 -> Ouro | F23: =ROUND(('Criaturas - Base de Dados'!H5*'Sistema de Raridade e Evolução'!E5)*1000,2) -> 288000 | G23: =ROUND('Criaturas - Base de Dados'!I5*'Sistema de Raridade e Evolução'!E5,0) -> 180 | H23: =ROUND('Criaturas - Base de Dados'!J5*'Sistema de Raridade e Evolução'!E5,0) -> 144 | I23: =ROUND('Criaturas - Base de Dados'!K5*'Sistema de Raridade e Evolução'!E5,0) -> 918 | J23: ='Sistema de Raridade e Evolução'!D5 -> 31 | K23: Lendário | L23: =ROUND(F23*(2.5/1.05),2) -> 685714.29
A24: 23 | B24: ='Criaturas - Base de Dados'!B5 -> Ordem Celestial | C24: ='Criaturas - Base de Dados'!C5 -> Luz | D24: ='Criaturas - Base de Dados'!D5 -> Serpente-Pluma Ancestral | E24: ='Sistema de Raridade e Evolução'!B6 -> Platina | F24: =ROUND(('Criaturas - Base de Dados'!H5*'Sistema de Raridade e Evolução'!E6)*1000,2) -> 800000 | G24: =ROUND('Criaturas - Base de Dados'!I5*'Sistema de Raridade e Evolução'!E6,0) -> 500 | H24: =ROUND('Criaturas - Base de Dados'!J5*'Sistema de Raridade e Evolução'!E6,0) -> 400 | I24: =ROUND('Criaturas - Base de Dados'!K5*'Sistema de Raridade e Evolução'!E6,0) -> 2550 | J24: ='Sistema de Raridade e Evolução'!D6 -> 56 | K24: Mítico | L24: =ROUND(F24*(2.5/1.05),2) -> 1904761.9
A25: 24 | B25: ='Criaturas - Base de Dados'!B5 -> Ordem Celestial | C25: ='Criaturas - Base de Dados'!C5 -> Luz | D25: ='Criaturas - Base de Dados'!D5 -> Serpente-Pluma Ancestral | E25: ='Sistema de Raridade e Evolução'!B7 -> Lendário | F25: =ROUND(('Criaturas - Base de Dados'!H5*'Sistema de Raridade e Evolução'!E7)*1000,2) -> 2400000 | G25: =ROUND('Criaturas - Base de Dados'!I5*'Sistema de Raridade e Evolução'!E7,0) -> 1500 | H25: =ROUND('Criaturas - Base de Dados'!J5*'Sistema de Raridade e Evolução'!E7,0) -> 1200 | I25: =ROUND('Criaturas - Base de Dados'!K5*'Sistema de Raridade e Evolução'!E7,0) -> 7650 | J25: ='Sistema de Raridade e Evolução'!D7 -> 91 | K25: MÁXIMO | L25: =ROUND(F25*(2.5/1.05),2) -> 5714285.7
A26: 25 | B26: ='Criaturas - Base de Dados'!B6 -> Ordem Celestial | C26: ='Criaturas - Base de Dados'!C6 -> Luz | D26: ='Criaturas - Base de Dados'!D6 -> Unicórnio Sagrado | E26: ='Sistema de Raridade e Evolução'!B2 -> Default | F26: =ROUND(('Criaturas - Base de Dados'!H6*'Sistema de Raridade e Evolução'!E2)*1000,2) -> #VALUE! | G26: =ROUND('Criaturas - Base de Dados'!I6*'Sistema de Raridade e Evolução'!E2,0) -> #VALUE! | H26: =ROUND('Criaturas - Base de Dados'!J6*'Sistema de Raridade e Evolução'!E2,0) -> #VALUE! | I26: =ROUND('Criaturas - Base de Dados'!K6*'Sistema de Raridade e Evolução'!E2,0) -> #VALUE! | J26: ='Sistema de Raridade e Evolução'!D2 -> 1 | K26: Prata | L26: =ROUND(F26*(2.5/1.05),2) -> #VALUE!
A27: 26 | B27: ='Criaturas - Base de Dados'!B6 -> Ordem Celestial | C27: ='Criaturas - Base de Dados'!C6 -> Luz | D27: ='Criaturas - Base de Dados'!D6 -> Unicórnio Sagrado | E27: ='Sistema de Raridade e Evolução'!B3 -> Bronze | F27: =ROUND(('Criaturas - Base de Dados'!H6*'Sistema de Raridade e Evolução'!E3)*1000,2) -> 16000 | G27: =ROUND('Criaturas - Base de Dados'!I6*'Sistema de Raridade e Evolução'!E3,0) -> 10 | H27: =ROUND('Criaturas - Base de Dados'!J6*'Sistema de Raridade e Evolução'!E3,0) -> 8 | I27: =ROUND('Criaturas - Base de Dados'!K6*'Sistema de Raridade e Evolução'!E3,0) -> 51 | J27: ='Sistema de Raridade e Evolução'!D3 -> 6 | K27: Ouro | L27: =ROUND(F27*(2.5/1.05),2) -> 38095.24
A28: 27 | B28: ='Criaturas - Base de Dados'!B6 -> Ordem Celestial | C28: ='Criaturas - Base de Dados'!C6 -> Luz | D28: ='Criaturas - Base de Dados'!D6 -> Unicórnio Sagrado | E28: ='Sistema de Raridade e Evolução'!B4 -> Prata | F28: =ROUND(('Criaturas - Base de Dados'!H6*'Sistema de Raridade e Evolução'!E4)*1000,2) -> 96000 | G28: =ROUND('Criaturas - Base de Dados'!I6*'Sistema de Raridade e Evolução'!E4,0) -> 60 | H28: =ROUND('Criaturas - Base de Dados'!J6*'Sistema de Raridade e Evolução'!E4,0) -> 48 | I28: =ROUND('Criaturas - Base de Dados'!K6*'Sistema de Raridade e Evolução'!E4,0) -> 306 | J28: ='Sistema de Raridade e Evolução'!D4 -> 16 | K28: Platina | L28: =ROUND(F28*(2.5/1.05),2) -> 228571.43
A29: 28 | B29: ='Criaturas - Base de Dados'!B6 -> Ordem Celestial | C29: ='Criaturas - Base de Dados'!C6 -> Luz | D29: ='Criaturas - Base de Dados'!D6 -> Unicórnio Sagrado | E29: ='Sistema de Raridade e Evolução'!B5 -> Ouro | F29: =ROUND(('Criaturas - Base de Dados'!H6*'Sistema de Raridade e Evolução'!E5)*1000,2) -> 288000 | G29: =ROUND('Criaturas - Base de Dados'!I6*'Sistema de Raridade e Evolução'!E5,0) -> 180 | H29: =ROUND('Criaturas - Base de Dados'!J6*'Sistema de Raridade e Evolução'!E5,0) -> 144 | I29: =ROUND('Criaturas - Base de Dados'!K6*'Sistema de Raridade e Evolução'!E5,0) -> 918 | J29: ='Sistema de Raridade e Evolução'!D5 -> 31 | K29: Lendário | L29: =ROUND(F29*(2.5/1.05),2) -> 685714.29
A30: 29 | B30: ='Criaturas - Base de Dados'!B6 -> Ordem Celestial | C30: ='Criaturas - Base de Dados'!C6 -> Luz | D30: ='Criaturas - Base de Dados'!D6 -> Unicórnio Sagrado | E30: ='Sistema de Raridade e Evolução'!B6 -> Platina | F30: =ROUND(('Criaturas - Base de Dados'!H6*'Sistema de Raridade e Evolução'!E6)*1000,2) -> 800000 | G30: =ROUND('Criaturas - Base de Dados'!I6*'Sistema de Raridade e Evolução'!E6,0) -> 500 | H30: =ROUND('Criaturas - Base de Dados'!J6*'Sistema de Raridade e Evolução'!E6,0) -> 400 | I30: =ROUND('Criaturas - Base de Dados'!K6*'Sistema de Raridade e Evolução'!E6,0) -> 2550 | J30: ='Sistema de Raridade e Evolução'!D6 -> 56 | K30: Mítico | L30: =ROUND(F30*(2.5/1.05),2) -> 1904761.9
A31: 30 | B31: ='Criaturas - Base de Dados'!B6 -> Ordem Celestial | C31: ='Criaturas - Base de Dados'!C6 -> Luz | D31: ='Criaturas - Base de Dados'!D6 -> Unicórnio Sagrado | E31: ='Sistema de Raridade e Evolução'!B7 -> Lendário | F31: =ROUND(('Criaturas - Base de Dados'!H6*'Sistema de Raridade e Evolução'!E7)*1000,2) -> 2400000 | G31: =ROUND('Criaturas - Base de Dados'!I6*'Sistema de Raridade e Evolução'!E7,0) -> 1500 | H31: =ROUND('Criaturas - Base de Dados'!J6*'Sistema de Raridade e Evolução'!E7,0) -> 1200 | I31: =ROUND('Criaturas - Base de Dados'!K6*'Sistema de Raridade e Evolução'!E7,0) -> 7650 | J31: ='Sistema de Raridade e Evolução'!D7 -> 91 | K31: MÁXIMO | L31: =ROUND(F31*(2.5/1.05),2) -> 5714285.7
A32: 31 | B32: ='Criaturas - Base de Dados'!B7 -> Ordem Celestial | C32: ='Criaturas - Base de Dados'!C7 -> Luz | D32: ='Criaturas - Base de Dados'!D7 -> Roc Celestial | E32: ='Sistema de Raridade e Evolução'!B2 -> Default | F32: =ROUND(('Criaturas - Base de Dados'!H7*'Sistema de Raridade e Evolução'!E2)*1000,2) -> #VALUE! | G32: =ROUND('Criaturas - Base de Dados'!I7*'Sistema de Raridade e Evolução'!E2,0) -> #VALUE! | H32: =ROUND('Criaturas - Base de Dados'!J7*'Sistema de Raridade e Evolução'!E2,0) -> #VALUE! | I32: =ROUND('Criaturas - Base de Dados'!K7*'Sistema de Raridade e Evolução'!E2,0) -> #VALUE! | J32: ='Sistema de Raridade e Evolução'!D2 -> 1 | K32: Prata | L32: =ROUND(F32*(2.5/1.05),2) -> #VALUE!
A33: 32 | B33: ='Criaturas - Base de Dados'!B7 -> Ordem Celestial | C33: ='Criaturas - Base de Dados'!C7 -> Luz | D33: ='Criaturas - Base de Dados'!D7 -> Roc Celestial | E33: ='Sistema de Raridade e Evolução'!B3 -> Bronze | F33: =ROUND(('Criaturas - Base de Dados'!H7*'Sistema de Raridade e Evolução'!E3)*1000,2) -> 18000 | G33: =ROUND('Criaturas - Base de Dados'!I7*'Sistema de Raridade e Evolução'!E3,0) -> 11 | H33: =ROUND('Criaturas - Base de Dados'!J7*'Sistema de Raridade e Evolução'!E3,0) -> 9 | I33: =ROUND('Criaturas - Base de Dados'!K7*'Sistema de Raridade e Evolução'!E3,0) -> 58 | J33: ='Sistema de Raridade e Evolução'!D3 -> 6 | K33: Ouro | L33: =ROUND(F33*(2.5/1.05),2) -> 42857.14
A34: 33 | B34: ='Criaturas - Base de Dados'!B7 -> Ordem Celestial | C34: ='Criaturas - Base de Dados'!C7 -> Luz | D34: ='Criaturas - Base de Dados'!D7 -> Roc Celestial | E34: ='Sistema de Raridade e Evolução'!B4 -> Prata | F34: =ROUND(('Criaturas - Base de Dados'!H7*'Sistema de Raridade e Evolução'!E4)*1000,2) -> 108000 | G34: =ROUND('Criaturas - Base de Dados'!I7*'Sistema de Raridade e Evolução'!E4,0) -> 66 | H34: =ROUND('Criaturas - Base de Dados'!J7*'Sistema de Raridade e Evolução'!E4,0) -> 54 | I34: =ROUND('Criaturas - Base de Dados'!K7*'Sistema de Raridade e Evolução'!E4,0) -> 348 | J34: ='Sistema de Raridade e Evolução'!D4 -> 16 | K34: Platina | L34: =ROUND(F34*(2.5/1.05),2) -> 257142.86
A35: 34 | B35: ='Criaturas - Base de Dados'!B7 -> Ordem Celestial | C35: ='Criaturas - Base de Dados'!C7 -> Luz | D35: ='Criaturas - Base de Dados'!D7 -> Roc Celestial | E35: ='Sistema de Raridade e Evolução'!B5 -> Ouro | F35: =ROUND(('Criaturas - Base de Dados'!H7*'Sistema de Raridade e Evolução'!E5)*1000,2) -> 324000 | G35: =ROUND('Criaturas - Base de Dados'!I7*'Sistema de Raridade e Evolução'!E5,0) -> 198 | H35: =ROUND('Criaturas - Base de Dados'!J7*'Sistema de Raridade e Evolução'!E5,0) -> 162 | I35: =ROUND('Criaturas - Base de Dados'!K7*'Sistema de Raridade e Evolução'!E5,0) -> 1044 | J35: ='Sistema de Raridade e Evolução'!D5 -> 31 | K35: Lendário | L35: =ROUND(F35*(2.5/1.05),2) -> 771428.57
A36: 35 | B36: ='Criaturas - Base de Dados'!B7 -> Ordem Celestial | C36: ='Criaturas - Base de Dados'!C7 -> Luz | D36: ='Criaturas - Base de Dados'!D7 -> Roc Celestial | E36: ='Sistema de Raridade e Evolução'!B6 -> Platina | F36: =ROUND(('Criaturas - Base de Dados'!H7*'Sistema de Raridade e Evolução'!E6)*1000,2) -> 900000 | G36: =ROUND('Criaturas - Base de Dados'!I7*'Sistema de Raridade e Evolução'!E6,0) -> 550 | H36: =ROUND('Criaturas - Base de Dados'!J7*'Sistema de Raridade e Evolução'!E6,0) -> 450 | I36: =ROUND('Criaturas - Base de Dados'!K7*'Sistema de Raridade e Evolução'!E6,0) -> 2900 | J36: ='Sistema de Raridade e Evolução'!D6 -> 56 | K36: Mítico | L36: =ROUND(F36*(2.5/1.05),2) -> 2142857.1
A37: 36 | B37: ='Criaturas - Base de Dados'!B7 -> Ordem Celestial | C37: ='Criaturas - Base de Dados'!C7 -> Luz | D37: ='Criaturas - Base de Dados'!D7 -> Roc Celestial | E37: ='Sistema de Raridade e Evolução'!B7 -> Lendário | F37: =ROUND(('Criaturas - Base de Dados'!H7*'Sistema de Raridade e Evolução'!E7)*1000,2) -> 2700000 | G37: =ROUND('Criaturas - Base de Dados'!I7*'Sistema de Raridade e Evolução'!E7,0) -> 1650 | H37: =ROUND('Criaturas - Base de Dados'!J7*'Sistema de Raridade e Evolução'!E7,0) -> 1350 | I37: =ROUND('Criaturas - Base de Dados'!K7*'Sistema de Raridade e Evolução'!E7,0) -> 8700 | J37: ='Sistema de Raridade e Evolução'!D7 -> 91 | K37: MÁXIMO | L37: =ROUND(F37*(2.5/1.05),2) -> 6428571.4
A38: 37 | B38: ='Criaturas - Base de Dados'!B8 -> Ordem Celestial | C38: ='Criaturas - Base de Dados'!C8 -> Luz | D38: ='Criaturas - Base de Dados'!D8 -> Lamassu Dourado | E38: ='Sistema de Raridade e Evolução'!B2 -> Default | F38: =ROUND(('Criaturas - Base de Dados'!H8*'Sistema de Raridade e Evolução'!E2)*1000,2) -> #VALUE! | G38: =ROUND('Criaturas - Base de Dados'!I8*'Sistema de Raridade e Evolução'!E2,0) -> #VALUE! | H38: =ROUND('Criaturas - Base de Dados'!J8*'Sistema de Raridade e Evolução'!E2,0) -> #VALUE! | I38: =ROUND('Criaturas - Base de Dados'!K8*'Sistema de Raridade e Evolução'!E2,0) -> #VALUE! | J38: ='Sistema de Raridade e Evolução'!D2 -> 1 | K38: Prata | L38: =ROUND(F38*(2.5/1.05),2) -> #VALUE!
A39: 38 | B39: ='Criaturas - Base de Dados'!B8 -> Ordem Celestial | C39: ='Criaturas - Base de Dados'!C8 -> Luz | D39: ='Criaturas - Base de Dados'!D8 -> Lamassu Dourado | E39: ='Sistema de Raridade e Evolução'!B3 -> Bronze | F39: =ROUND(('Criaturas - Base de Dados'!H8*'Sistema de Raridade e Evolução'!E3)*1000,2) -> 20000 | G39: =ROUND('Criaturas - Base de Dados'!I8*'Sistema de Raridade e Evolução'!E3,0) -> 12 | H39: =ROUND('Criaturas - Base de Dados'!J8*'Sistema de Raridade e Evolução'!E3,0) -> 10 | I39: =ROUND('Criaturas - Base de Dados'!K8*'Sistema de Raridade e Evolução'!E3,0) -> 64 | J39: ='Sistema de Raridade e Evolução'!D3 -> 6 | K39: Ouro | L39: =ROUND(F39*(2.5/1.05),2) -> 47619.05
A40: 39 | B40: ='Criaturas - Base de Dados'!B8 -> Ordem Celestial | C40: ='Criaturas - Base de Dados'!C8 -> Luz | D40: ='Criaturas - Base de Dados'!D8 -> Lamassu Dourado | E40: ='Sistema de Raridade e Evolução'!B4 -> Prata | F40: =ROUND(('Criaturas - Base de Dados'!H8*'Sistema de Raridade e Evolução'!E4)*1000,2) -> 120000 | G40: =ROUND('Criaturas - Base de Dados'!I8*'Sistema de Raridade e Evolução'!E4,0) -> 72 | H40: =ROUND('Criaturas - Base de Dados'!J8*'Sistema de Raridade e Evolução'!E4,0) -> 60 | I40: =ROUND('Criaturas - Base de Dados'!K8*'Sistema de Raridade e Evolução'!E4,0) -> 384 | J40: ='Sistema de Raridade e Evolução'!D4 -> 16 | K40: Platina | L40: =ROUND(F40*(2.5/1.05),2) -> 285714.29
A41: 40 | B41: ='Criaturas - Base de Dados'!B8 -> Ordem Celestial | C41: ='Criaturas - Base de Dados'!C8 -> Luz | D41: ='Criaturas - Base de Dados'!D8 -> Lamassu Dourado | E41: ='Sistema de Raridade e Evolução'!B5 -> Ouro | F41: =ROUND(('Criaturas - Base de Dados'!H8*'Sistema de Raridade e Evolução'!E5)*1000,2) -> 360000 | G41: =ROUND('Criaturas - Base de Dados'!I8*'Sistema de Raridade e Evolução'!E5,0) -> 216 | H41: =ROUND('Criaturas - Base de Dados'!J8*'Sistema de Raridade e Evolução'!E5,0) -> 180 | I41: =ROUND('Criaturas - Base de Dados'!K8*'Sistema de Raridade e Evolução'!E5,0) -> 1152 | J41: ='Sistema de Raridade e Evolução'!D5 -> 31 | K41: Lendário | L41: =ROUND(F41*(2.5/1.05),2) -> 857142.86
A42: 41 | B42: ='Criaturas - Base de Dados'!B8 -> Ordem Celestial | C42: ='Criaturas - Base de Dados'!C8 -> Luz | D42: ='Criaturas - Base de Dados'!D8 -> Lamassu Dourado | E42: ='Sistema de Raridade e Evolução'!B6 -> Platina | F42: =ROUND(('Criaturas - Base de Dados'!H8*'Sistema de Raridade e Evolução'!E6)*1000,2) -> 1000000 | G42: =ROUND('Criaturas - Base de Dados'!I8*'Sistema de Raridade e Evolução'!E6,0) -> 600 | H42: =ROUND('Criaturas - Base de Dados'!J8*'Sistema de Raridade e Evolução'!E6,0) -> 500 | I42: =ROUND('Criaturas - Base de Dados'!K8*'Sistema de Raridade e Evolução'!E6,0) -> 3200 | J42: ='Sistema de Raridade e Evolução'!D6 -> 56 | K42: Mítico | L42: =ROUND(F42*(2.5/1.05),2) -> 2380952.4
A43: 42 | B43: ='Criaturas - Base de Dados'!B8 -> Ordem Celestial | C43: ='Criaturas - Base de Dados'!C8 -> Luz | D43: ='Criaturas - Base de Dados'!D8 -> Lamassu Dourado | E43: ='Sistema de Raridade e Evolução'!B7 -> Lendário | F43: =ROUND(('Criaturas - Base de Dados'!H8*'Sistema de Raridade e Evolução'!E7)*1000,2) -> 3000000 | G43: =ROUND('Criaturas - Base de Dados'!I8*'Sistema de Raridade e Evolução'!E7,0) -> 1800 | H43: =ROUND('Criaturas - Base de Dados'!J8*'Sistema de Raridade e Evolução'!E7,0) -> 1500 | I43: =ROUND('Criaturas - Base de Dados'!K8*'Sistema de Raridade e Evolução'!E7,0) -> 9600 | J43: ='Sistema de Raridade e Evolução'!D7 -> 91 | K43: MÁXIMO | L43: =ROUND(F43*(2.5/1.05),2) -> 7142857.1
A44: 43 | B44: ='Criaturas - Base de Dados'!B9 -> Ordem Celestial | C44: ='Criaturas - Base de Dados'!C9 -> Luz | D44: ='Criaturas - Base de Dados'!D9 -> Bennu Ancestral | E44: ='Sistema de Raridade e Evolução'!B2 -> Default | F44: =ROUND(('Criaturas - Base de Dados'!H9*'Sistema de Raridade e Evolução'!E2)*1000,2) -> #VALUE! | G44: =ROUND('Criaturas - Base de Dados'!I9*'Sistema de Raridade e Evolução'!E2,0) -> #VALUE! | H44: =ROUND('Criaturas - Base de Dados'!J9*'Sistema de Raridade e Evolução'!E2,0) -> #VALUE! | I44: =ROUND('Criaturas - Base de Dados'!K9*'Sistema de Raridade e Evolução'!E2,0) -> #VALUE! | J44: ='Sistema de Raridade e Evolução'!D2 -> 1 | K44: Prata | L44: =ROUND(F44*(2.5/1.05),2) -> #VALUE!
A45: 44 | B45: ='Criaturas - Base de Dados'!B9 -> Ordem Celestial | C45: ='Criaturas - Base de Dados'!C9 -> Luz | D45: ='Criaturas - Base de Dados'!D9 -> Bennu Ancestral | E45: ='Sistema de Raridade e Evolução'!B3 -> Bronze | F45: =ROUND(('Criaturas - Base de Dados'!H9*'Sistema de Raridade e Evolução'!E3)*1000,2) -> 22000 | G45: =ROUND('Criaturas - Base de Dados'!I9*'Sistema de Raridade e Evolução'!E3,0) -> 13 | H45: =ROUND('Criaturas - Base de Dados'!J9*'Sistema de Raridade e Evolução'!E3,0) -> 11 | I45: =ROUND('Criaturas - Base de Dados'!K9*'Sistema de Raridade e Evolução'!E3,0) -> 70 | J45: ='Sistema de Raridade e Evolução'!D3 -> 6 | K45: Ouro | L45: =ROUND(F45*(2.5/1.05),2) -> 52380.95
A46: 45 | B46: ='Criaturas - Base de Dados'!B9 -> Ordem Celestial | C46: ='Criaturas - Base de Dados'!C9 -> Luz | D46: ='Criaturas - Base de Dados'!D9 -> Bennu Ancestral | E46: ='Sistema de Raridade e Evolução'!B4 -> Prata | F46: =ROUND(('Criaturas - Base de Dados'!H9*'Sistema de Raridade e Evolução'!E4)*1000,2) -> 132000 | G46: =ROUND('Criaturas - Base de Dados'!I9*'Sistema de Raridade e Evolução'!E4,0) -> 78 | H46: =ROUND('Criaturas - Base de Dados'!J9*'Sistema de Raridade e Evolução'!E4,0) -> 66 | I46: =ROUND('Criaturas - Base de Dados'!K9*'Sistema de Raridade e Evolução'!E4,0) -> 420 | J46: ='Sistema de Raridade e Evolução'!D4 -> 16 | K46: Platina | L46: =ROUND(F46*(2.5/1.05),2) -> 314285.71
A47: 46 | B47: ='Criaturas - Base de Dados'!B9 -> Ordem Celestial | C47: ='Criaturas - Base de Dados'!C9 -> Luz | D47: ='Criaturas - Base de Dados'!D9 -> Bennu Ancestral | E47: ='Sistema de Raridade e Evolução'!B5 -> Ouro | F47: =ROUND(('Criaturas - Base de Dados'!H9*'Sistema de Raridade e Evolução'!E5)*1000,2) -> 396000 | G47: =ROUND('Criaturas - Base de Dados'!I9*'Sistema de Raridade e Evolução'!E5,0) -> 234 | H47: =ROUND('Criaturas - Base de Dados'!J9*'Sistema de Raridade e Evolução'!E5,0) -> 198 | I47: =ROUND('Criaturas - Base de Dados'!K9*'Sistema de Raridade e Evolução'!E5,0) -> 1260 | J47: ='Sistema de Raridade e Evolução'!D5 -> 31 | K47: Lendário | L47: =ROUND(F47*(2.5/1.05),2) -> 942857.14
A48: 47 | B48: ='Criaturas - Base de Dados'!B9 -> Ordem Celestial | C48: ='Criaturas - Base de Dados'!C9 -> Luz | D48: ='Criaturas - Base de Dados'!D9 -> Bennu Ancestral | E48: ='Sistema de Raridade e Evolução'!B6 -> Platina | F48: =ROUND(('Criaturas - Base de Dados'!H9*'Sistema de Raridade e Evolução'!E6)*1000,2) -> 1100000 | G48: =ROUND('Criaturas - Base de Dados'!I9*'Sistema de Raridade e Evolução'!E6,0) -> 650 | H48: =ROUND('Criaturas - Base de Dados'!J9*'Sistema de Raridade e Evolução'!E6,0) -> 550 | I48: =ROUND('Criaturas - Base de Dados'!K9*'Sistema de Raridade e Evolução'!E6,0) -> 3500 | J48: ='Sistema de Raridade e Evolução'!D6 -> 56 | K48: Mítico | L48: =ROUND(F48*(2.5/1.05),2) -> 2619047.6
A49: 48 | B49: ='Criaturas - Base de Dados'!B9 -> Ordem Celestial | C49: ='Criaturas - Base de Dados'!C9 -> Luz | D49: ='Criaturas - Base de Dados'!D9 -> Bennu Ancestral | E49: ='Sistema de Raridade e Evolução'!B7 -> Lendário | F49: =ROUND(('Criaturas - Base de Dados'!H9*'Sistema de Raridade e Evolução'!E7)*1000,2) -> 3300000 | G49: =ROUND('Criaturas - Base de Dados'!I9*'Sistema de Raridade e Evolução'!E7,0) -> 1950 | H49: =ROUND('Criaturas - Base de Dados'!J9*'Sistema de Raridade e Evolução'!E7,0) -> 1650 | I49: =ROUND('Criaturas - Base de Dados'!K9*'Sistema de Raridade e Evolução'!E7,0) -> 10500 | J49: ='Sistema de Raridade e Evolução'!D7 -> 91 | K49: MÁXIMO | L49: =ROUND(F49*(2.5/1.05),2) -> 7857142.9
A50: 49 | B50: ='Criaturas - Base de Dados'!B10 -> Ordem Celestial | C50: ='Criaturas - Base de Dados'!C10 -> Luz | D50: ='Criaturas - Base de Dados'!D10 -> Garuda Radiante | E50: ='Sistema de Raridade e Evolução'!B2 -> Default | F50: =ROUND(('Criaturas - Base de Dados'!H10*'Sistema de Raridade e Evolução'!E2)*1000,2) -> #VALUE! | G50: =ROUND('Criaturas - Base de Dados'!I10*'Sistema de Raridade e Evolução'!E2,0) -> #VALUE! | H50: =ROUND('Criaturas - Base de Dados'!J10*'Sistema de Raridade e Evolução'!E2,0) -> #VALUE! | I50: =ROUND('Criaturas - Base de Dados'!K10*'Sistema de Raridade e Evolução'!E2,0) -> #VALUE! | J50: ='Sistema de Raridade e Evolução'!D2 -> 1 | K50: Prata | L50: =ROUND(F50*(2.5/1.05),2) -> #VALUE!
A51: 50 | B51: ='Criaturas - Base de Dados'!B10 -> Ordem Celestial | C51: ='Criaturas - Base de Dados'!C10 -> Luz | D51: ='Criaturas - Base de Dados'!D10 -> Garuda Radiante | E51: ='Sistema de Raridade e Evolução'!B3 -> Bronze | F51: =ROUND(('Criaturas - Base de Dados'!H10*'Sistema de Raridade e Evolução'!E3)*1000,2) -> 24000 | G51: =ROUND('Criaturas - Base de Dados'!I10*'Sistema de Raridade e Evolução'!E3,0) -> 14 | H51: =ROUND('Criaturas - Base de Dados'!J10*'Sistema de Raridade e Evolução'!E3,0) -> 12 | I51: =ROUND('Criaturas - Base de Dados'!K10*'Sistema de Raridade e Evolução'!E3,0) -> 77 | J51: ='Sistema de Raridade e Evolução'!D3 -> 6 | K51: Ouro | L51: =ROUND(F51*(2.5/1.05),2) -> 57142.86
A52: 51 | B52: ='Criaturas - Base de Dados'!B10 -> Ordem Celestial | C52: ='Criaturas - Base de Dados'!C10 -> Luz | D52: ='Criaturas - Base de Dados'!D10 -> Garuda Radiante | E52: ='Sistema de Raridade e Evolução'!B4 -> Prata | F52: =ROUND(('Criaturas - Base de Dados'!H10*'Sistema de Raridade e Evolução'!E4)*1000,2) -> 144000 | G52: =ROUND('Criaturas - Base de Dados'!I10*'Sistema de Raridade e Evolução'!E4,0) -> 84 | H52: =ROUND('Criaturas - Base de Dados'!J10*'Sistema de Raridade e Evolução'!E4,0) -> 72 | I52: =ROUND('Criaturas - Base de Dados'!K10*'Sistema de Raridade e Evolução'!E4,0) -> 462 | J52: ='Sistema de Raridade e Evolução'!D4 -> 16 | K52: Platina | L52: =ROUND(F52*(2.5/1.05),2) -> 342857.14
A53: 52 | B53: ='Criaturas - Base de Dados'!B10 -> Ordem Celestial | C53: ='Criaturas - Base de Dados'!C10 -> Luz | D53: ='Criaturas - Base de Dados'!D10 -> Garuda Radiante | E53: ='Sistema de Raridade e Evolução'!B5 -> Ouro | F53: =ROUND(('Criaturas - Base de Dados'!H10*'Sistema de Raridade e Evolução'!E5)*1000,2) -> 432000 | G53: =ROUND('Criaturas - Base de Dados'!I10*'Sistema de Raridade e Evolução'!E5,0) -> 252 | H53: =ROUND('Criaturas - Base de Dados'!J10*'Sistema de Raridade e Evolução'!E5,0) -> 216 | I53: =ROUND('Criaturas - Base de Dados'!K10*'Sistema de Raridade e Evolução'!E5,0) -> 1386 | J53: ='Sistema de Raridade e Evolução'!D5 -> 31 | K53: Lendário | L53: =ROUND(F53*(2.5/1.05),2) -> 1028571.4
A54: 53 | B54: ='Criaturas - Base de Dados'!B10 -> Ordem Celestial | C54: ='Criaturas - Base de Dados'!C10 -> Luz | D54: ='Criaturas - Base de Dados'!D10 -> Garuda Radiante | E54: ='Sistema de Raridade e Evolução'!B6 -> Platina | F54: =ROUND(('Criaturas - Base de Dados'!H10*'Sistema de Raridade e Evolução'!E6)*1000,2) -> 1200000 | G54: =ROUND('Criaturas - Base de Dados'!I10*'Sistema de Raridade e Evolução'!E6,0) -> 700 | H54: =ROUND('Criaturas - Base de Dados'!J10*'Sistema de Raridade e Evolução'!E6,0) -> 600 | I54: =ROUND('Criaturas - Base de Dados'!K10*'Sistema de Raridade e Evolução'!E6,0) -> 3850 | J54: ='Sistema de Raridade e Evolução'!D6 -> 56 | K54: Mítico | L54: =ROUND(F54*(2.5/1.05),2) -> 2857142.9
A55: 54 | B55: ='Criaturas - Base de Dados'!B10 -> Ordem Celestial | C55: ='Criaturas - Base de Dados'!C10 -> Luz | D55: ='Criaturas - Base de Dados'!D10 -> Garuda Radiante | E55: ='Sistema de Raridade e Evolução'!B7 -> Lendário | F55: =ROUND(('Criaturas - Base de Dados'!H10*'Sistema de Raridade e Evolução'!E7)*1000,2) -> 3600000 | G55: =ROUND('Criaturas - Base de Dados'!I10*'Sistema de Raridade e Evolução'!E7,0) -> 2100 | H55: =ROUND('Criaturas - Base de Dados'!J10*'Sistema de Raridade e Evolução'!E7,0) -> 1800 | I55: =ROUND('Criaturas - Base de Dados'!K10*'Sistema de Raridade e Evolução'!E7,0) -> 11550 | J55: ='Sistema de Raridade e Evolução'!D7 -> 91 | K55: MÁXIMO | L55: =ROUND(F55*(2.5/1.05),2) -> 8571428.6
A56: 55 | B56: ='Criaturas - Base de Dados'!B11 -> Ordem Celestial | C56: ='Criaturas - Base de Dados'!C11 -> Luz | D56: ='Criaturas - Base de Dados'!D11 -> Simurgh Eterno | E56: ='Sistema de Raridade e Evolução'!B2 -> Default | F56: =ROUND(('Criaturas - Base de Dados'!H11*'Sistema de Raridade e Evolução'!E2)*1000,2) -> #VALUE! | G56: =ROUND('Criaturas - Base de Dados'!I11*'Sistema de Raridade e Evolução'!E2,0) -> #VALUE! | H56: =ROUND('Criaturas - Base de Dados'!J11*'Sistema de Raridade e Evolução'!E2,0) -> #VALUE! | I56: =ROUND('Criaturas - Base de Dados'!K11*'Sistema de Raridade e Evolução'!E2,0) -> #VALUE! | J56: ='Sistema de Raridade e Evolução'!D2 -> 1 | K56: Prata | L56: =ROUND(F56*(2.5/1.05),2) -> #VALUE!
A57: 56 | B57: ='Criaturas - Base de Dados'!B11 -> Ordem Celestial | C57: ='Criaturas - Base de Dados'!C11 -> Luz | D57: ='Criaturas - Base de Dados'!D11 -> Simurgh Eterno | E57: ='Sistema de Raridade e Evolução'!B3 -> Bronze | F57: =ROUND(('Criaturas - Base de Dados'!H11*'Sistema de Raridade e Evolução'!E3)*1000,2) -> 26000 | G57: =ROUND('Criaturas - Base de Dados'!I11*'Sistema de Raridade e Evolução'!E3,0) -> 16 | H57: =ROUND('Criaturas - Base de Dados'!J11*'Sistema de Raridade e Evolução'!E3,0) -> 13 | I57: =ROUND('Criaturas - Base de Dados'!K11*'Sistema de Raridade e Evolução'!E3,0) -> 83 | J57: ='Sistema de Raridade e Evolução'!D3 -> 6 | K57: Ouro | L57: =ROUND(F57*(2.5/1.05),2) -> 61904.76
A58: 57 | B58: ='Criaturas - Base de Dados'!B11 -> Ordem Celestial | C58: ='Criaturas - Base de Dados'!C11 -> Luz | D58: ='Criaturas - Base de Dados'!D11 -> Simurgh Eterno | E58: ='Sistema de Raridade e Evolução'!B4 -> Prata | F58: =ROUND(('Criaturas - Base de Dados'!H11*'Sistema de Raridade e Evolução'!E4)*1000,2) -> 156000 | G58: =ROUND('Criaturas - Base de Dados'!I11*'Sistema de Raridade e Evolução'!E4,0) -> 96 | H58: =ROUND('Criaturas - Base de Dados'!J11*'Sistema de Raridade e Evolução'!E4,0) -> 78 | I58: =ROUND('Criaturas - Base de Dados'!K11*'Sistema de Raridade e Evolução'!E4,0) -> 498 | J58: ='Sistema de Raridade e Evolução'!D4 -> 16 | K58: Platina | L58: =ROUND(F58*(2.5/1.05),2) -> 371428.57
A59: 58 | B59: ='Criaturas - Base de Dados'!B11 -> Ordem Celestial | C59: ='Criaturas - Base de Dados'!C11 -> Luz | D59: ='Criaturas - Base de Dados'!D11 -> Simurgh Eterno | E59: ='Sistema de Raridade e Evolução'!B5 -> Ouro | F59: =ROUND(('Criaturas - Base de Dados'!H11*'Sistema de Raridade e Evolução'!E5)*1000,2) -> 468000 | G59: =ROUND('Criaturas - Base de Dados'!I11*'Sistema de Raridade e Evolução'!E5,0) -> 288 | H59: =ROUND('Criaturas - Base de Dados'!J11*'Sistema de Raridade e Evolução'!E5,0) -> 234 | I59: =ROUND('Criaturas - Base de Dados'!K11*'Sistema de Raridade e Evolução'!E5,0) -> 1494 | J59: ='Sistema de Raridade e Evolução'!D5 -> 31 | K59: Lendário | L59: =ROUND(F59*(2.5/1.05),2) -> 1114285.7
A60: 59 | B60: ='Criaturas - Base de Dados'!B11 -> Ordem Celestial | C60: ='Criaturas - Base de Dados'!C11 -> Luz | D60: ='Criaturas - Base de Dados'!D11 -> Simurgh Eterno | E60: ='Sistema de Raridade e Evolução'!B6 -> Platina | F60: =ROUND(('Criaturas - Base de Dados'!H11*'Sistema de Raridade e Evolução'!E6)*1000,2) -> 1300000 | G60: =ROUND('Criaturas - Base de Dados'!I11*'Sistema de Raridade e Evolução'!E6,0) -> 800 | H60: =ROUND('Criaturas - Base de Dados'!J11*'Sistema de Raridade e Evolução'!E6,0) -> 650 | I60: =ROUND('Criaturas - Base de Dados'!K11*'Sistema de Raridade e Evolução'!E6,0) -> 4150 | J60: ='Sistema de Raridade e Evolução'!D6 -> 56 | K60: Mítico | L60: =ROUND(F60*(2.5/1.05),2) -> 3095238.1
A61: 60 | B61: ='Criaturas - Base de Dados'!B11 -> Ordem Celestial | C61: ='Criaturas - Base de Dados'!C11 -> Luz | D61: ='Criaturas - Base de Dados'!D11 -> Simurgh Eterno | E61: ='Sistema de Raridade e Evolução'!B7 -> Lendário | F61: =ROUND(('Criaturas - Base de Dados'!H11*'Sistema de Raridade e Evolução'!E7)*1000,2) -> 3900000 | G61: =ROUND('Criaturas - Base de Dados'!I11*'Sistema de Raridade e Evolução'!E7,0) -> 2400 | H61: =ROUND('Criaturas - Base de Dados'!J11*'Sistema de Raridade e Evolução'!E7,0) -> 1950 | I61: =ROUND('Criaturas - Base de Dados'!K11*'Sistema de Raridade e Evolução'!E7,0) -> 12450 | J61: ='Sistema de Raridade e Evolução'!D7 -> 91 | K61: MÁXIMO | L61: =ROUND(F61*(2.5/1.05),2) -> 9285714.3
A62: 61 | B62: ='Criaturas - Base de Dados'!B12 -> Ordem Celestial | C62: ='Criaturas - Base de Dados'!C12 -> Luz | D62: ='Criaturas - Base de Dados'!D12 -> Kirin Puro | E62: ='Sistema de Raridade e Evolução'!B2 -> Default | F62: =ROUND(('Criaturas - Base de Dados'!H12*'Sistema de Raridade e Evolução'!E2)*1000,2) -> #VALUE! | G62: =ROUND('Criaturas - Base de Dados'!I12*'Sistema de Raridade e Evolução'!E2,0) -> #VALUE! | H62: =ROUND('Criaturas - Base de Dados'!J12*'Sistema de Raridade e Evolução'!E2,0) -> #VALUE! | I62: =ROUND('Criaturas - Base de Dados'!K12*'Sistema de Raridade e Evolução'!E2,0) -> #VALUE! | J62: ='Sistema de Raridade e Evolução'!D2 -> 1 | K62: Prata | L62: =ROUND(F62*(2.5/1.05),2) -> #VALUE!
A63: 62 | B63: ='Criaturas - Base de Dados'!B12 -> Ordem Celestial | C63: ='Criaturas - Base de Dados'!C12 -> Luz | D63: ='Criaturas - Base de Dados'!D12 -> Kirin Puro | E63: ='Sistema de Raridade e Evolução'!B3 -> Bronze | F63: =ROUND(('Criaturas - Base de Dados'!H12*'Sistema de Raridade e Evolução'!E3)*1000,2) -> 28000 | G63: =ROUND('Criaturas - Base de Dados'!I12*'Sistema de Raridade e Evolução'!E3,0) -> 17 | H63: =ROUND('Criaturas - Base de Dados'!J12*'Sistema de Raridade e Evolução'!E3,0) -> 14 | I63: =ROUND('Criaturas - Base de Dados'!K12*'Sistema de Raridade e Evolução'!E3,0) -> 90 | J63: ='Sistema de Raridade e Evolução'!D3 -> 6 | K63: Ouro | L63: =ROUND(F63*(2.5/1.05),2) -> 66666.67
A64: 63 | B64: ='Criaturas - Base de Dados'!B12 -> Ordem Celestial | C64: ='Criaturas - Base de Dados'!C12 -> Luz | D64: ='Criaturas - Base de Dados'!D12 -> Kirin Puro | E64: ='Sistema de Raridade e Evolução'!B4 -> Prata | F64: =ROUND(('Criaturas - Base de Dados'!H12*'Sistema de Raridade e Evolução'!E4)*1000,2) -> 168000 | G64: =ROUND('Criaturas - Base de Dados'!I12*'Sistema de Raridade e Evolução'!E4,0) -> 102 | H64: =ROUND('Criaturas - Base de Dados'!J12*'Sistema de Raridade e Evolução'!E4,0) -> 84 | I64: =ROUND('Criaturas - Base de Dados'!K12*'Sistema de Raridade e Evolução'!E4,0) -> 540 | J64: ='Sistema de Raridade e Evolução'!D4 -> 16 | K64: Platina | L64: =ROUND(F64*(2.5/1.05),2) -> 400000
A65: 64 | B65: ='Criaturas - Base de Dados'!B12 -> Ordem Celestial | C65: ='Criaturas - Base de Dados'!C12 -> Luz | D65: ='Criaturas - Base de Dados'!D12 -> Kirin Puro | E65: ='Sistema de Raridade e Evolução'!B5 -> Ouro | F65: =ROUND(('Criaturas - Base de Dados'!H12*'Sistema de Raridade e Evolução'!E5)*1000,2) -> 504000 | G65: =ROUND('Criaturas - Base de Dados'!I12*'Sistema de Raridade e Evolução'!E5,0) -> 306 | H65: =ROUND('Criaturas - Base de Dados'!J12*'Sistema de Raridade e Evolução'!E5,0) -> 252 | I65: =ROUND('Criaturas - Base de Dados'!K12*'Sistema de Raridade e Evolução'!E5,0) -> 1620 | J65: ='Sistema de Raridade e Evolução'!D5 -> 31 | K65: Lendário | L65: =ROUND(F65*(2.5/1.05),2) -> 1200000
A66: 65 | B66: ='Criaturas - Base de Dados'!B12 -> Ordem Celestial | C66: ='Criaturas - Base de Dados'!C12 -> Luz | D66: ='Criaturas - Base de Dados'!D12 -> Kirin Puro | E66: ='Sistema de Raridade e Evolução'!B6 -> Platina | F66: =ROUND(('Criaturas - Base de Dados'!H12*'Sistema de Raridade e Evolução'!E6)*1000,2) -> 1400000 | G66: =ROUND('Criaturas - Base de Dados'!I12*'Sistema de Raridade e Evolução'!E6,0) -> 850 | H66: =ROUND('Criaturas - Base de Dados'!J12*'Sistema de Raridade e Evolução'!E6,0) -> 700 | I66: =ROUND('Criaturas - Base de Dados'!K12*'Sistema de Raridade e Evolução'!E6,0) -> 4500 | J66: ='Sistema de Raridade e Evolução'!D6 -> 56 | K66: Mítico | L66: =ROUND(F66*(2.5/1.05),2) -> 3333333.3
A67: 66 | B67: ='Criaturas - Base de Dados'!B12 -> Ordem Celestial | C67: ='Criaturas - Base de Dados'!C12 -> Luz | D67: ='Criaturas - Base de Dados'!D12 -> Kirin Puro | E67: ='Sistema de Raridade e Evolução'!B7 -> Lendário | F67: =ROUND(('Criaturas - Base de Dados'!H12*'Sistema de Raridade e Evolução'!E7)*1000,2) -> 4200000 | G67: =ROUND('Criaturas - Base de Dados'!I12*'Sistema de Raridade e Evolução'!E7,0) -> 2550 | H67: =ROUND('Criaturas - Base de Dados'!J12*'Sistema de Raridade e Evolução'!E7,0) -> 2100 | I67: =ROUND('Criaturas - Base de Dados'!K12*'Sistema de Raridade e Evolução'!E7,0) -> 13500 | J67: ='Sistema de Raridade e Evolução'!D7 -> 91 | K67: MÁXIMO | L67: =ROUND(F67*(2.5/1.05),2) -> 10000000
A68: 67 | B68: ='Criaturas - Base de Dados'!B13 -> Ordem Celestial | C68: ='Criaturas - Base de Dados'!C13 -> Luz | D68: ='Criaturas - Base de Dados'!D13 -> Huma Abençoada | E68: ='Sistema de Raridade e Evolução'!B2 -> Default | F68: =ROUND(('Criaturas - Base de Dados'!H13*'Sistema de Raridade e Evolução'!E2)*1000,2) -> #VALUE! | G68: =ROUND('Criaturas - Base de Dados'!I13*'Sistema de Raridade e Evolução'!E2,0) -> #VALUE! | H68: =ROUND('Criaturas - Base de Dados'!J13*'Sistema de Raridade e Evolução'!E2,0) -> #VALUE! | I68: =ROUND('Criaturas - Base de Dados'!K13*'Sistema de Raridade e Evolução'!E2,0) -> #VALUE! | J68: ='Sistema de Raridade e Evolução'!D2 -> 1 | K68: Prata | L68: =ROUND(F68*(2.5/1.05),2) -> #VALUE!
A69: 68 | B69: ='Criaturas - Base de Dados'!B13 -> Ordem Celestial | C69: ='Criaturas - Base de Dados'!C13 -> Luz | D69: ='Criaturas - Base de Dados'!D13 -> Huma Abençoada | E69: ='Sistema de Raridade e Evolução'!B3 -> Bronze | F69: =ROUND(('Criaturas - Base de Dados'!H13*'Sistema de Raridade e Evolução'!E3)*1000,2) -> 30000 | G69: =ROUND('Criaturas - Base de Dados'!I13*'Sistema de Raridade e Evolução'!E3,0) -> 18 | H69: =ROUND('Criaturas - Base de Dados'!J13*'Sistema de Raridade e Evolução'!E3,0) -> 15 | I69: =ROUND('Criaturas - Base de Dados'!K13*'Sistema de Raridade e Evolução'!E3,0) -> 96 | J69: ='Sistema de Raridade e Evolução'!D3 -> 6 | K69: Ouro | L69: =ROUND(F69*(2.5/1.05),2) -> 71428.57
A70: 69 | B70: ='Criaturas - Base de Dados'!B13 -> Ordem Celestial | C70: ='Criaturas - Base de Dados'!C13 -> Luz | D70: ='Criaturas - Base de Dados'!D13 -> Huma Abençoada | E70: ='Sistema de Raridade e Evolução'!B4 -> Prata | F70: =ROUND(('Criaturas - Base de Dados'!H13*'Sistema de Raridade e Evolução'!E4)*1000,2) -> 180000 | G70: =ROUND('Criaturas - Base de Dados'!I13*'Sistema de Raridade e Evolução'!E4,0) -> 108 | H70: =ROUND('Criaturas - Base de Dados'!J13*'Sistema de Raridade e Evolução'!E4,0) -> 90 | I70: =ROUND('Criaturas - Base de Dados'!K13*'Sistema de Raridade e Evolução'!E4,0) -> 576 | J70: ='Sistema de Raridade e Evolução'!D4 -> 16 | K70: Platina | L70: =ROUND(F70*(2.5/1.05),2) -> 428571.43
A71: 70 | B71: ='Criaturas - Base de Dados'!B13 -> Ordem Celestial | C71: ='Criaturas - Base de Dados'!C13 -> Luz | D71: ='Criaturas - Base de Dados'!D13 -> Huma Abençoada | E71: ='Sistema de Raridade e Evolução'!B5 -> Ouro | F71: =ROUND(('Criaturas - Base de Dados'!H13*'Sistema de Raridade e Evolução'!E5)*1000,2) -> 540000 | G71: =ROUND('Criaturas - Base de Dados'!I13*'Sistema de Raridade e Evolução'!E5,0) -> 324 | H71: =ROUND('Criaturas - Base de Dados'!J13*'Sistema de Raridade e Evolução'!E5,0) -> 270 | I71: =ROUND('Criaturas - Base de Dados'!K13*'Sistema de Raridade e Evolução'!E5,0) -> 1728 | J71: ='Sistema de Raridade e Evolução'!D5 -> 31 | K71: Lendário | L71: =ROUND(F71*(2.5/1.05),2) -> 1285714.3
A72: 71 | B72: ='Criaturas - Base de Dados'!B13 -> Ordem Celestial | C72: ='Criaturas - Base de Dados'!C13 -> Luz | D72: ='Criaturas - Base de Dados'!D13 -> Huma Abençoada | E72: ='Sistema de Raridade e Evolução'!B6 -> Platina | F72: =ROUND(('Criaturas - Base de Dados'!H13*'Sistema de Raridade e Evolução'!E6)*1000,2) -> 1500000 | G72: =ROUND('Criaturas - Base de Dados'!I13*'Sistema de Raridade e Evolução'!E6,0) -> 900 | H72: =ROUND('Criaturas - Base de Dados'!J13*'Sistema de Raridade e Evolução'!E6,0) -> 750 | I72: =ROUND('Criaturas - Base de Dados'!K13*'Sistema de Raridade e Evolução'!E6,0) -> 4800 | J72: ='Sistema de Raridade e Evolução'!D6 -> 56 | K72: Mítico | L72: =ROUND(F72*(2.5/1.05),2) -> 3571428.6
A73: 72 | B73: ='Criaturas - Base de Dados'!B13 -> Ordem Celestial | C73: ='Criaturas - Base de Dados'!C13 -> Luz | D73: ='Criaturas - Base de Dados'!D13 -> Huma Abençoada | E73: ='Sistema de Raridade e Evolução'!B7 -> Lendário | F73: =ROUND(('Criaturas - Base de Dados'!H13*'Sistema de Raridade e Evolução'!E7)*1000,2) -> 4500000 | G73: =ROUND('Criaturas - Base de Dados'!I13*'Sistema de Raridade e Evolução'!E7,0) -> 2700 | H73: =ROUND('Criaturas - Base de Dados'!J13*'Sistema de Raridade e Evolução'!E7,0) -> 2250 | I73: =ROUND('Criaturas - Base de Dados'!K13*'Sistema de Raridade e Evolução'!E7,0) -> 14400 | J73: ='Sistema de Raridade e Evolução'!D7 -> 91 | K73: MÁXIMO | L73: =ROUND(F73*(2.5/1.05),2) -> 10714286
A74: 73 | B74: ='Criaturas - Base de Dados'!B14 -> Ordem Celestial | C74: ='Criaturas - Base de Dados'!C14 -> Luz | D74: ='Criaturas - Base de Dados'!D14 -> Peri da Luz | E74: ='Sistema de Raridade e Evolução'!B2 -> Default | F74: =ROUND(('Criaturas - Base de Dados'!H14*'Sistema de Raridade e Evolução'!E2)*1000,2) -> #VALUE! | G74: =ROUND('Criaturas - Base de Dados'!I14*'Sistema de Raridade e Evolução'!E2,0) -> #VALUE! | H74: =ROUND('Criaturas - Base de Dados'!J14*'Sistema de Raridade e Evolução'!E2,0) -> #VALUE! | I74: =ROUND('Criaturas - Base de Dados'!K14*'Sistema de Raridade e Evolução'!E2,0) -> #VALUE! | J74: ='Sistema de Raridade e Evolução'!D2 -> 1 | K74: Prata | L74: =ROUND(F74*(2.5/1.05),2) -> #VALUE!
A75: 74 | B75: ='Criaturas - Base de Dados'!B14 -> Ordem Celestial | C75: ='Criaturas - Base de Dados'!C14 -> Luz | D75: ='Criaturas - Base de Dados'!D14 -> Peri da Luz | E75: ='Sistema de Raridade e Evolução'!B3 -> Bronze | F75: =ROUND(('Criaturas - Base de Dados'!H14*'Sistema de Raridade e Evolução'!E3)*1000,2) -> 34000 | G75: =ROUND('Criaturas - Base de Dados'!I14*'Sistema de Raridade e Evolução'!E3,0) -> 20 | H75: =ROUND('Criaturas - Base de Dados'!J14*'Sistema de Raridade e Evolução'!E3,0) -> 17 | I75: =ROUND('Criaturas - Base de Dados'!K14*'Sistema de Raridade e Evolução'!E3,0) -> 109 | J75: ='Sistema de Raridade e Evolução'!D3 -> 6 | K75: Ouro | L75: =ROUND(F75*(2.5/1.05),2) -> 80952.38
A76: 75 | B76: ='Criaturas - Base de Dados'!B14 -> Ordem Celestial | C76: ='Criaturas - Base de Dados'!C14 -> Luz | D76: ='Criaturas - Base de Dados'!D14 -> Peri da Luz | E76: ='Sistema de Raridade e Evolução'!B4 -> Prata | F76: =ROUND(('Criaturas - Base de Dados'!H14*'Sistema de Raridade e Evolução'!E4)*1000,2) -> 204000 | G76: =ROUND('Criaturas - Base de Dados'!I14*'Sistema de Raridade e Evolução'!E4,0) -> 120 | H76: =ROUND('Criaturas - Base de Dados'!J14*'Sistema de Raridade e Evolução'!E4,0) -> 102 | I76: =ROUND('Criaturas - Base de Dados'!K14*'Sistema de Raridade e Evolução'!E4,0) -> 654 | J76: ='Sistema de Raridade e Evolução'!D4 -> 16 | K76: Platina | L76: =ROUND(F76*(2.5/1.05),2) -> 485714.29
A77: 76 | B77: ='Criaturas - Base de Dados'!B14 -> Ordem Celestial | C77: ='Criaturas - Base de Dados'!C14 -> Luz | D77: ='Criaturas - Base de Dados'!D14 -> Peri da Luz | E77: ='Sistema de Raridade e Evolução'!B5 -> Ouro | F77: =ROUND(('Criaturas - Base de Dados'!H14*'Sistema de Raridade e Evolução'!E5)*1000,2) -> 612000 | G77: =ROUND('Criaturas - Base de Dados'!I14*'Sistema de Raridade e Evolução'!E5,0) -> 360 | H77: =ROUND('Criaturas - Base de Dados'!J14*'Sistema de Raridade e Evolução'!E5,0) -> 306 | I77: =ROUND('Criaturas - Base de Dados'!K14*'Sistema de Raridade e Evolução'!E5,0) -> 1962 | J77: ='Sistema de Raridade e Evolução'!D5 -> 31 | K77: Lendário | L77: =ROUND(F77*(2.5/1.05),2) -> 1457142.9
A78: 77 | B78: ='Criaturas - Base de Dados'!B14 -> Ordem Celestial | C78: ='Criaturas - Base de Dados'!C14 -> Luz | D78: ='Criaturas - Base de Dados'!D14 -> Peri da Luz | E78: ='Sistema de Raridade e Evolução'!B6 -> Platina | F78: =ROUND(('Criaturas - Base de Dados'!H14*'Sistema de Raridade e Evolução'!E6)*1000,2) -> 1700000 | G78: =ROUND('Criaturas - Base de Dados'!I14*'Sistema de Raridade e Evolução'!E6,0) -> 1000 | H78: =ROUND('Criaturas - Base de Dados'!J14*'Sistema de Raridade e Evolução'!E6,0) -> 850 | I78: =ROUND('Criaturas - Base de Dados'!K14*'Sistema de Raridade e Evolução'!E6,0) -> 5450 | J78: ='Sistema de Raridade e Evolução'!D6 -> 56 | K78: Mítico | L78: =ROUND(F78*(2.5/1.05),2) -> 4047619
A79: 78 | B79: ='Criaturas - Base de Dados'!B14 -> Ordem Celestial | C79: ='Criaturas - Base de Dados'!C14 -> Luz | D79: ='Criaturas - Base de Dados'!D14 -> Peri da Luz | E79: ='Sistema de Raridade e Evolução'!B7 -> Lendário | F79: =ROUND(('Criaturas - Base de Dados'!H14*'Sistema de Raridade e Evolução'!E7)*1000,2) -> 5100000 | G79: =ROUND('Criaturas - Base de Dados'!I14*'Sistema de Raridade e Evolução'!E7,0) -> 3000 | H79: =ROUND('Criaturas - Base de Dados'!J14*'Sistema de Raridade e Evolução'!E7,0) -> 2550 | I79: =ROUND('Criaturas - Base de Dados'!K14*'Sistema de Raridade e Evolução'!E7,0) -> 16350 | J79: ='Sistema de Raridade e Evolução'!D7 -> 91 | K79: MÁXIMO | L79: =ROUND(F79*(2.5/1.05),2) -> 12142857
A80: 79 | B80: ='Criaturas - Base de Dados'!B15 -> Ordem Celestial | C80: ='Criaturas - Base de Dados'!C15 -> Luz | D80: ='Criaturas - Base de Dados'!D15 -> Serafim de Seis Asas | E80: ='Sistema de Raridade e Evolução'!B2 -> Default | F80: =ROUND(('Criaturas - Base de Dados'!H15*'Sistema de Raridade e Evolução'!E2)*1000,2) -> #VALUE! | G80: =ROUND('Criaturas - Base de Dados'!I15*'Sistema de Raridade e Evolução'!E2,0) -> #VALUE! | H80: =ROUND('Criaturas - Base de Dados'!J15*'Sistema de Raridade e Evolução'!E2,0) -> #VALUE! | I80: =ROUND('Criaturas - Base de Dados'!K15*'Sistema de Raridade e Evolução'!E2,0) -> #VALUE! | J80: ='Sistema de Raridade e Evolução'!D2 -> 1 | K80: Prata | L80: =ROUND(F80*(2.5/1.05),2) -> #VALUE!
A81: 80 | B81: ='Criaturas - Base de Dados'!B15 -> Ordem Celestial | C81: ='Criaturas - Base de Dados'!C15 -> Luz | D81: ='Criaturas - Base de Dados'!D15 -> Serafim de Seis Asas | E81: ='Sistema de Raridade e Evolução'!B3 -> Bronze | F81: =ROUND(('Criaturas - Base de Dados'!H15*'Sistema de Raridade e Evolução'!E3)*1000,2) -> 36000 | G81: =ROUND('Criaturas - Base de Dados'!I15*'Sistema de Raridade e Evolução'!E3,0) -> 22 | H81: =ROUND('Criaturas - Base de Dados'!J15*'Sistema de Raridade e Evolução'!E3,0) -> 18 | I81: =ROUND('Criaturas - Base de Dados'!K15*'Sistema de Raridade e Evolução'!E3,0) -> 115 | J81: ='Sistema de Raridade e Evolução'!D3 -> 6 | K81: Ouro | L81: =ROUND(F81*(2.5/1.05),2) -> 85714.29
A82: 81 | B82: ='Criaturas - Base de Dados'!B15 -> Ordem Celestial | C82: ='Criaturas - Base de Dados'!C15 -> Luz | D82: ='Criaturas - Base de Dados'!D15 -> Serafim de Seis Asas | E82: ='Sistema de Raridade e Evolução'!B4 -> Prata | F82: =ROUND(('Criaturas - Base de Dados'!H15*'Sistema de Raridade e Evolução'!E4)*1000,2) -> 216000 | G82: =ROUND('Criaturas - Base de Dados'!I15*'Sistema de Raridade e Evolução'!E4,0) -> 132 | H82: =ROUND('Criaturas - Base de Dados'!J15*'Sistema de Raridade e Evolução'!E4,0) -> 108 | I82: =ROUND('Criaturas - Base de Dados'!K15*'Sistema de Raridade e Evolução'!E4,0) -> 690 | J82: ='Sistema de Raridade e Evolução'!D4 -> 16 | K82: Platina | L82: =ROUND(F82*(2.5/1.05),2) -> 514285.71
A83: 82 | B83: ='Criaturas - Base de Dados'!B15 -> Ordem Celestial | C83: ='Criaturas - Base de Dados'!C15 -> Luz | D83: ='Criaturas - Base de Dados'!D15 -> Serafim de Seis Asas | E83: ='Sistema de Raridade e Evolução'!B5 -> Ouro | F83: =ROUND(('Criaturas - Base de Dados'!H15*'Sistema de Raridade e Evolução'!E5)*1000,2) -> 648000 | G83: =ROUND('Criaturas - Base de Dados'!I15*'Sistema de Raridade e Evolução'!E5,0) -> 396 | H83: =ROUND('Criaturas - Base de Dados'!J15*'Sistema de Raridade e Evolução'!E5,0) -> 324 | I83: =ROUND('Criaturas - Base de Dados'!K15*'Sistema de Raridade e Evolução'!E5,0) -> 2070 | J83: ='Sistema de Raridade e Evolução'!D5 -> 31 | K83: Lendário | L83: =ROUND(F83*(2.5/1.05),2) -> 1542857.1
A84: 83 | B84: ='Criaturas - Base de Dados'!B15 -> Ordem Celestial | C84: ='Criaturas - Base de Dados'!C15 -> Luz | D84: ='Criaturas - Base de Dados'!D15 -> Serafim de Seis Asas | E84: ='Sistema de Raridade e Evolução'!B6 -> Platina | F84: =ROUND(('Criaturas - Base de Dados'!H15*'Sistema de Raridade e Evolução'!E6)*1000,2) -> 1800000 | G84: =ROUND('Criaturas - Base de Dados'!I15*'Sistema de Raridade e Evolução'!E6,0) -> 1100 | H84: =ROUND('Criaturas - Base de Dados'!J15*'Sistema de Raridade e Evolução'!E6,0) -> 900 | I84: =ROUND('Criaturas - Base de Dados'!K15*'Sistema de Raridade e Evolução'!E6,0) -> 5750 | J84: ='Sistema de Raridade e Evolução'!D6 -> 56 | K84: Mítico | L84: =ROUND(F84*(2.5/1.05),2) -> 4285714.3
A85: 84 | B85: ='Criaturas - Base de Dados'!B15 -> Ordem Celestial | C85: ='Criaturas - Base de Dados'!C15 -> Luz | D85: ='Criaturas - Base de Dados'!D15 -> Serafim de Seis Asas | E85: ='Sistema de Raridade e Evolução'!B7 -> Lendário | F85: =ROUND(('Criaturas - Base de Dados'!H15*'Sistema de Raridade e Evolução'!E7)*1000,2) -> 5400000 | G85: =ROUND('Criaturas - Base de Dados'!I15*'Sistema de Raridade e Evolução'!E7,0) -> 3300 | H85: =ROUND('Criaturas - Base de Dados'!J15*'Sistema de Raridade e Evolução'!E7,0) -> 2700 | I85: =ROUND('Criaturas - Base de Dados'!K15*'Sistema de Raridade e Evolução'!E7,0) -> 17250 | J85: ='Sistema de Raridade e Evolução'!D7 -> 91 | K85: MÁXIMO | L85: =ROUND(F85*(2.5/1.05),2) -> 12857143
A86: 85 | B86: ='Criaturas - Base de Dados'!B16 -> Ordem Celestial | C86: ='Criaturas - Base de Dados'!C16 -> Luz | D86: ='Criaturas - Base de Dados'!D16 -> Ave-Sol Inca | E86: ='Sistema de Raridade e Evolução'!B2 -> Default | F86: =ROUND(('Criaturas - Base de Dados'!H16*'Sistema de Raridade e Evolução'!E2)*1000,2) -> #VALUE! | G86: =ROUND('Criaturas - Base de Dados'!I16*'Sistema de Raridade e Evolução'!E2,0) -> #VALUE! | H86: =ROUND('Criaturas - Base de Dados'!J16*'Sistema de Raridade e Evolução'!E2,0) -> #VALUE! | I86: =ROUND('Criaturas - Base de Dados'!K16*'Sistema de Raridade e Evolução'!E2,0) -> #VALUE! | J86: ='Sistema de Raridade e Evolução'!D2 -> 1 | K86: Prata | L86: =ROUND(F86*(2.5/1.05),2) -> #VALUE!
A87: 86 | B87: ='Criaturas - Base de Dados'!B16 -> Ordem Celestial | C87: ='Criaturas - Base de Dados'!C16 -> Luz | D87: ='Criaturas - Base de Dados'!D16 -> Ave-Sol Inca | E87: ='Sistema de Raridade e Evolução'!B3 -> Bronze | F87: =ROUND(('Criaturas - Base de Dados'!H16*'Sistema de Raridade e Evolução'!E3)*1000,2) -> 38000 | G87: =ROUND('Criaturas - Base de Dados'!I16*'Sistema de Raridade e Evolução'!E3,0) -> 23 | H87: =ROUND('Criaturas - Base de Dados'!J16*'Sistema de Raridade e Evolução'!E3,0) -> 19 | I87: =ROUND('Criaturas - Base de Dados'!K16*'Sistema de Raridade e Evolução'!E3,0) -> 122 | J87: ='Sistema de Raridade e Evolução'!D3 -> 6 | K87: Ouro | L87: =ROUND(F87*(2.5/1.05),2) -> 90476.19
A88: 87 | B88: ='Criaturas - Base de Dados'!B16 -> Ordem Celestial | C88: ='Criaturas - Base de Dados'!C16 -> Luz | D88: ='Criaturas - Base de Dados'!D16 -> Ave-Sol Inca | E88: ='Sistema de Raridade e Evolução'!B4 -> Prata | F88: =ROUND(('Criaturas - Base de Dados'!H16*'Sistema de Raridade e Evolução'!E4)*1000,2) -> 228000 | G88: =ROUND('Criaturas - Base de Dados'!I16*'Sistema de Raridade e Evolução'!E4,0) -> 138 | H88: =ROUND('Criaturas - Base de Dados'!J16*'Sistema de Raridade e Evolução'!E4,0) -> 114 | I88: =ROUND('Criaturas - Base de Dados'!K16*'Sistema de Raridade e Evolução'!E4,0) -> 732 | J88: ='Sistema de Raridade e Evolução'!D4 -> 16 | K88: Platina | L88: =ROUND(F88*(2.5/1.05),2) -> 542857.14
A89: 88 | B89: ='Criaturas - Base de Dados'!B16 -> Ordem Celestial | C89: ='Criaturas - Base de Dados'!C16 -> Luz | D89: ='Criaturas - Base de Dados'!D16 -> Ave-Sol Inca | E89: ='Sistema de Raridade e Evolução'!B5 -> Ouro | F89: =ROUND(('Criaturas - Base de Dados'!H16*'Sistema de Raridade e Evolução'!E5)*1000,2) -> 684000 | G89: =ROUND('Criaturas - Base de Dados'!I16*'Sistema de Raridade e Evolução'!E5,0) -> 414 | H89: =ROUND('Criaturas - Base de Dados'!J16*'Sistema de Raridade e Evolução'!E5,0) -> 342 | I89: =ROUND('Criaturas - Base de Dados'!K16*'Sistema de Raridade e Evolução'!E5,0) -> 2196 | J89: ='Sistema de Raridade e Evolução'!D5 -> 31 | K89: Lendário | L89: =ROUND(F89*(2.5/1.05),2) -> 1628571.4
A90: 89 | B90: ='Criaturas - Base de Dados'!B16 -> Ordem Celestial | C90: ='Criaturas - Base de Dados'!C16 -> Luz | D90: ='Criaturas - Base de Dados'!D16 -> Ave-Sol Inca | E90: ='Sistema de Raridade e Evolução'!B6 -> Platina | F90: =ROUND(('Criaturas - Base de Dados'!H16*'Sistema de Raridade e Evolução'!E6)*1000,2) -> 1900000 | G90: =ROUND('Criaturas - Base de Dados'!I16*'Sistema de Raridade e Evolução'!E6,0) -> 1150 | H90: =ROUND('Criaturas - Base de Dados'!J16*'Sistema de Raridade e Evolução'!E6,0) -> 950 | I90: =ROUND('Criaturas - Base de Dados'!K16*'Sistema de Raridade e Evolução'!E6,0) -> 6100 | J90: ='Sistema de Raridade e Evolução'!D6 -> 56 | K90: Mítico | L90: =ROUND(F90*(2.5/1.05),2) -> 4523809.5
A91: 90 | B91: ='Criaturas - Base de Dados'!B16 -> Ordem Celestial | C91: ='Criaturas - Base de Dados'!C16 -> Luz | D91: ='Criaturas - Base de Dados'!D16 -> Ave-Sol Inca | E91: ='Sistema de Raridade e Evolução'!B7 -> Lendário | F91: =ROUND(('Criaturas - Base de Dados'!H16*'Sistema de Raridade e Evolução'!E7)*1000,2) -> 5700000 | G91: =ROUND('Criaturas - Base de Dados'!I16*'Sistema de Raridade e Evolução'!E7,0) -> 3450 | H91: =ROUND('Criaturas - Base de Dados'!J16*'Sistema de Raridade e Evolução'!E7,0) -> 2850 | I91: =ROUND('Criaturas - Base de Dados'!K16*'Sistema de Raridade e Evolução'!E7,0) -> 18300 | J91: ='Sistema de Raridade e Evolução'!D7 -> 91 | K91: MÁXIMO | L91: =ROUND(F91*(2.5/1.05),2) -> 13571429
A92: 91 | B92: ='Criaturas - Base de Dados'!B17 -> Ordem Celestial | C92: ='Criaturas - Base de Dados'!C17 -> Luz | D92: ='Criaturas - Base de Dados'!D17 -> Alicanto Radiante | E92: ='Sistema de Raridade e Evolução'!B2 -> Default | F92: =ROUND(('Criaturas - Base de Dados'!H17*'Sistema de Raridade e Evolução'!E2)*1000,2) -> #VALUE! | G92: =ROUND('Criaturas - Base de Dados'!I17*'Sistema de Raridade e Evolução'!E2,0) -> #VALUE! | H92: =ROUND('Criaturas - Base de Dados'!J17*'Sistema de Raridade e Evolução'!E2,0) -> #VALUE! | I92: =ROUND('Criaturas - Base de Dados'!K17*'Sistema de Raridade e Evolução'!E2,0) -> #VALUE! | J92: ='Sistema de Raridade e Evolução'!D2 -> 1 | K92: Prata | L92: =ROUND(F92*(2.5/1.05),2) -> #VALUE!
A93: 92 | B93: ='Criaturas - Base de Dados'!B17 -> Ordem Celestial | C93: ='Criaturas - Base de Dados'!C17 -> Luz | D93: ='Criaturas - Base de Dados'!D17 -> Alicanto Radiante | E93: ='Sistema de Raridade e Evolução'!B3 -> Bronze | F93: =ROUND(('Criaturas - Base de Dados'!H17*'Sistema de Raridade e Evolução'!E3)*1000,2) -> 54000 | G93: =ROUND('Criaturas - Base de Dados'!I17*'Sistema de Raridade e Evolução'!E3,0) -> 32 | H93: =ROUND('Criaturas - Base de Dados'!J17*'Sistema de Raridade e Evolução'!E3,0) -> 27 | I93: =ROUND('Criaturas - Base de Dados'!K17*'Sistema de Raridade e Evolução'!E3,0) -> 173 | J93: ='Sistema de Raridade e Evolução'!D3 -> 6 | K93: Ouro | L93: =ROUND(F93*(2.5/1.05),2) -> 128571.43
A94: 93 | B94: ='Criaturas - Base de Dados'!B17 -> Ordem Celestial | C94: ='Criaturas - Base de Dados'!C17 -> Luz | D94: ='Criaturas - Base de Dados'!D17 -> Alicanto Radiante | E94: ='Sistema de Raridade e Evolução'!B4 -> Prata | F94: =ROUND(('Criaturas - Base de Dados'!H17*'Sistema de Raridade e Evolução'!E4)*1000,2) -> 324000 | G94: =ROUND('Criaturas - Base de Dados'!I17*'Sistema de Raridade e Evolução'!E4,0) -> 192 | H94: =ROUND('Criaturas - Base de Dados'!J17*'Sistema de Raridade e Evolução'!E4,0) -> 162 | I94: =ROUND('Criaturas - Base de Dados'!K17*'Sistema de Raridade e Evolução'!E4,0) -> 1038 | J94: ='Sistema de Raridade e Evolução'!D4 -> 16 | K94: Platina | L94: =ROUND(F94*(2.5/1.05),2) -> 771428.57
A95: 94 | B95: ='Criaturas - Base de Dados'!B17 -> Ordem Celestial | C95: ='Criaturas - Base de Dados'!C17 -> Luz | D95: ='Criaturas - Base de Dados'!D17 -> Alicanto Radiante | E95: ='Sistema de Raridade e Evolução'!B5 -> Ouro | F95: =ROUND(('Criaturas - Base de Dados'!H17*'Sistema de Raridade e Evolução'!E5)*1000,2) -> 972000 | G95: =ROUND('Criaturas - Base de Dados'!I17*'Sistema de Raridade e Evolução'!E5,0) -> 576 | H95: =ROUND('Criaturas - Base de Dados'!J17*'Sistema de Raridade e Evolução'!E5,0) -> 486 | I95: =ROUND('Criaturas - Base de Dados'!K17*'Sistema de Raridade e Evolução'!E5,0) -> 3114 | J95: ='Sistema de Raridade e Evolução'!D5 -> 31 | K95: Lendário | L95: =ROUND(F95*(2.5/1.05),2) -> 2314285.7
A96: 95 | B96: ='Criaturas - Base de Dados'!B17 -> Ordem Celestial | C96: ='Criaturas - Base de Dados'!C17 -> Luz | D96: ='Criaturas - Base de Dados'!D17 -> Alicanto Radiante | E96: ='Sistema de Raridade e Evolução'!B6 -> Platina | F96: =ROUND(('Criaturas - Base de Dados'!H17*'Sistema de Raridade e Evolução'!E6)*1000,2) -> 2700000 | G96: =ROUND('Criaturas - Base de Dados'!I17*'Sistema de Raridade e Evolução'!E6,0) -> 1600 | H96: =ROUND('Criaturas - Base de Dados'!J17*'Sistema de Raridade e Evolução'!E6,0) -> 1350 | I96: =ROUND('Criaturas - Base de Dados'!K17*'Sistema de Raridade e Evolução'!E6,0) -> 8650 | J96: ='Sistema de Raridade e Evolução'!D6 -> 56 | K96: Mítico | L96: =ROUND(F96*(2.5/1.05),2) -> 6428571.4
A97: 96 | B97: ='Criaturas - Base de Dados'!B17 -> Ordem Celestial | C97: ='Criaturas - Base de Dados'!C17 -> Luz | D97: ='Criaturas - Base de Dados'!D17 -> Alicanto Radiante | E97: ='Sistema de Raridade e Evolução'!B7 -> Lendário | F97: =ROUND(('Criaturas - Base de Dados'!H17*'Sistema de Raridade e Evolução'!E7)*1000,2) -> 8100000 | G97: =ROUND('Criaturas - Base de Dados'!I17*'Sistema de Raridade e Evolução'!E7,0) -> 4800 | H97: =ROUND('Criaturas - Base de Dados'!J17*'Sistema de Raridade e Evolução'!E7,0) -> 4050 | I97: =ROUND('Criaturas - Base de Dados'!K17*'Sistema de Raridade e Evolução'!E7,0) -> 25950 | J97: ='Sistema de Raridade e Evolução'!D7 -> 91 | K97: MÁXIMO | L97: =ROUND(F97*(2.5/1.05),2) -> 19285714
A98: 97 | B98: ='Criaturas - Base de Dados'!B18 -> Ordem Celestial | C98: ='Criaturas - Base de Dados'!C18 -> Luz | D98: ='Criaturas - Base de Dados'!D18 -> Aurora Ancestral | E98: ='Sistema de Raridade e Evolução'!B2 -> Default | F98: =ROUND(('Criaturas - Base de Dados'!H18*'Sistema de Raridade e Evolução'!E2)*1000,2) -> #VALUE! | G98: =ROUND('Criaturas - Base de Dados'!I18*'Sistema de Raridade e Evolução'!E2,0) -> #VALUE! | H98: =ROUND('Criaturas - Base de Dados'!J18*'Sistema de Raridade e Evolução'!E2,0) -> #VALUE! | I98: =ROUND('Criaturas - Base de Dados'!K18*'Sistema de Raridade e Evolução'!E2,0) -> #VALUE! | J98: ='Sistema de Raridade e Evolução'!D2 -> 1 | K98: Prata | L98: =ROUND(F98*(2.5/1.05),2) -> #VALUE!
A99: 98 | B99: ='Criaturas - Base de Dados'!B18 -> Ordem Celestial | C99: ='Criaturas - Base de Dados'!C18 -> Luz | D99: ='Criaturas - Base de Dados'!D18 -> Aurora Ancestral | E99: ='Sistema de Raridade e Evolução'!B3 -> Bronze | F99: =ROUND(('Criaturas - Base de Dados'!H18*'Sistema de Raridade e Evolução'!E3)*1000,2) -> 48000 | G99: =ROUND('Criaturas - Base de Dados'!I18*'Sistema de Raridade e Evolução'!E3,0) -> 29 | H99: =ROUND('Criaturas - Base de Dados'!J18*'Sistema de Raridade e Evolução'!E3,0) -> 24 | I99: =ROUND('Criaturas - Base de Dados'!K18*'Sistema de Raridade e Evolução'!E3,0) -> 154 | J99: ='Sistema de Raridade e Evolução'!D3 -> 6 | K99: Ouro | L99: =ROUND(F99*(2.5/1.05),2) -> 114285.71
A100: 99 | B100: ='Criaturas - Base de Dados'!B18 -> Ordem Celestial | C100: ='Criaturas - Base de Dados'!C18 -> Luz | D100: ='Criaturas - Base de Dados'!D18 -> Aurora Ancestral | E100: ='Sistema de Raridade e Evolução'!B4 -> Prata | F100: =ROUND(('Criaturas - Base de Dados'!H18*'Sistema de Raridade e Evolução'!E4)*1000,2) -> 288000 | G100: =ROUND('Criaturas - Base de Dados'!I18*'Sistema de Raridade e Evolução'!E4,0) -> 174 | H100: =ROUND('Criaturas - Base de Dados'!J18*'Sistema de Raridade e Evolução'!E4,0) -> 144 | I100: =ROUND('Criaturas - Base de Dados'!K18*'Sistema de Raridade e Evolução'!E4,0) -> 924 | J100: ='Sistema de Raridade e Evolução'!D4 -> 16 | K100: Platina | L100: =ROUND(F100*(2.5/1.05),2) -> 685714.29
...

Sheet Sistema de Despertar (Grau)
A1: Grau | B1: Multiplicador de Valor/Stats | C1: Chance de Sair no Altar (%)
A2: — (vazio, default) | B2: 1 | C2: N/A — estado inicial, sem tentativa no Altar ainda
A3: 7 | B3: 1.05 | C3: 40
A4: 7.5 | B4: 1.15 | C4: 27
A5: 8 | B5: 1.3 | C5: 17
A6: 8.5 | B6: 1.5 | C6: 9
A7: 9 | B7: 1.75 | C7: 4.5
A8: 9.5 | B8: 2.1 | C8: 2
A9: 10 | B9: 2.5 | C9: 0.5
A10: Checagem: soma das chances 7.0→10.0 deve ser 100% | C10: =SUM(C3:C9) -> 100
A12: Regras do Despertar:
A13: - Toda carta nasce SEM despertar ativo (grau vazio). Nesse estado, o "quadradinho" de grau não aparece na UI — só surge a partir do primeiro despertar bem-sucedido (7.0+).
A14: - Custo por tentativa no Altar AUMENTA conforme a raridade da carta (ver tabela "Custo de Despertar por Raridade" abaixo).
A15: - O resultado sorteado SEMPRE substitui o grau atual, pra melhor OU PRA PIOR — risco real a cada tentativa (downgrade entre 7.0 e 10.0 é possível; não regride para vazio).
A16: - Valor final da carta = Valor Base (seedValue x multiplicador de Raridade) x Multiplicador de Grau.
A17: - Grau 7.0 tem ganho pequeno mas real (x1.05) — garante que o jogador nunca gasta Diamante à toa.
A19: Custo de Despertar por Raridade (Diamantes por tentativa):
A20: Raridade | B20: Custo (Diamantes)
A21: Bronze | B21: 1200
A22: Prata | B22: 2100
A23: Ouro | B23: 3300
A24: Platina | B24: 4800
A25: Lendário | B25: 6300
A26: Mítico | B26: 10000
A27: Divino | B27: 25000

Sheet Diamante do Índice
A1: Raridade Descoberta | B1: Diamante Ganho (1ª vez)
A2: Bronze | B2: 5
A3: Prata | B3: 10
A4: Ouro | B4: 25
A5: Platina | B5: 60
A6: Lendário | B6: 150
A7: Mítico | B7: 400
A9: Divino (bônus separado — só 15 existem, 1 por clã) | B9: 1000
A11: Diamante é ganho só na PRIMEIRA vez que uma combinação criatura+raridade é descoberta (1.800 descobertas possíveis Bronze→Mítico, + 15 Divinas à parte).
A12: Total máximo de Diamante via Índice (300 criaturas x cada raridade Bronze→Mítico descoberta 1x):
A13: Diamante total possível (Bronze→Mítico): | B13: =300*B2+300*B3+300*B4+300*B5+300*B6+300*B7 -> 195000
A14: Diamante total possível (Divino, 15 criaturas): | B14: =15*B9 -> 15000

Sheet Criaturas Divinas (Evento)
A1: # | B1: Clã | C1: Elemento | D1: Criatura Divina | E1: Origem Mitológica/Cultural | F1: Descrição breve | G1: Valor Semente ($/s) | H1: Ataque Base | I1: Defesa Base | J1: HP Base | K1: Como Obter | L1: Multiplicador (Divino)
A2: 1 | B2: Ordem Celestial | C2: Luz | D2: Amaterasu | E2: Japão (Xintoísmo) | F2: Deusa suprema do sol que ilumina todos os reinos | G2: 90 | H2: 54 | I2: 44 | J2: 260 | K2: Pacote Divino (Evento/Robux) | L2: 10000
A3: 2 | B3: Véu Sombrio | C3: Sombra | D3: Hécate | E3: Grécia | F3: Deusa das encruzilhadas, magia e noite | G3: 92 | H3: 55 | I3: 45 | J3: 262 | K3: Pacote Divino (Evento/Robux) | L3: 10000
A4: 3 | B4: Fúria Selvagem | C4: Natureza | D4: Cernunnos | E4: Celta | F4: Senhor cornífero da floresta e das feras | G4: 91 | H4: 56 | I4: 46 | J4: 265 | K4: Pacote Divino (Evento/Robux) | L4: 10000
A5: 4 | B5: Abismo Glacial | C5: Gelo | D5: Skadi | E5: Nórdica | F5: Deusa caçadora do inverno eterno | G5: 93 | H5: 55 | I5: 47 | J5: 268 | K5: Pacote Divino (Evento/Robux) | L5: 10000
A6: 5 | B6: Maré Eterna | C6: Água | D6: Poseidon | E6: Grécia | F6: Deus supremo dos mares e do tridente | G6: 94 | H6: 54 | I6: 48 | J6: 270 | K6: Pacote Divino (Evento/Robux) | L6: 10000
A7: 6 | B7: Forja Ígnea | C7: Fogo | D7: Agni | E7: Índia (Hinduísmo) | F7: Deus do fogo sagrado e purificador | G7: 89 | H7: 57 | I7: 43 | J7: 258 | K7: Pacote Divino (Evento/Robux) | L7: 10000
A8: 7 | B8: Tempestade Rúnica | C8: Trovão | D8: Raijin | E8: Japão (Xintoísmo) | F8: Deus da tempestade e dos trovões divinos | G8: 95 | H8: 58 | I8: 46 | J8: 272 | K8: Pacote Divino (Evento/Robux) | L8: 10000
A9: 8 | B9: Rocha Ancestral | C9: Terra | D9: Gaia | E9: Grécia | F9: Titã primordial da terra e geradora de vida | G9: 88 | H9: 52 | I9: 50 | J9: 275 | K9: Pacote Divino (Evento/Robux) | L9: 10000
A10: 9 | B10: Areia Amaldiçoada | C10: Morte | D10: Anubis | E10: Egito | F10: Deus da morte, guardião de túmulos e ressurreição | G10: 87 | H10: 53 | I10: 51 | J10: 280 | K10: Pacote Divino (Evento/Robux) | L10: 10000
A11: 10 | B11: Selva Esmeralda | C11: Veneno | D11: Shesha Naga | E11: Índia (Hinduísmo) | F11: Serpente cósmica de mil cabeças, guardiã das profundezas | G11: 96 | H11: 59 | I11: 45 | J11: 276 | K11: Pacote Divino (Evento/Robux) | L11: 10000
A12: 11 | B12: Constelação Arcana | C12: Astral | D12: Nuwa | E12: China | F12: Deusa criadora do universo e dos céus estrelados | G12: 97 | H12: 56 | I12: 49 | J12: 278 | K12: Pacote Divino (Evento/Robux) | L12: 10000
A13: 12 | B13: Profundezas Abissais | C13: Mar Profundo | D13: Cthulhu | E13: Mitologia Cósmica (Lovecraft - Domínio Público em 2026) | F13: Titã submerso de poder incompreensível | G13: 98 | H13: 60 | I13: 52 | J13: 290 | K13: Pacote Divino (Evento/Robux) | L13: 10000
... A16: 15 | B16: Engrenagem Rúnica | C16: Tecnomancia | D16: Thoth | E16: Egito | F16: Deus da sabedoria, magia rúnica e conhecimento cósmico | G16: 99 | H16: 55 | I16: 53 | J16: 288 | K16: Pacote Divino (Evento/Robux) | L16: 10000

Sheet Pacotes - Parâmetros
A1: Parâmetros do Sistema de Pacotes
A3: Raridade | B3: Multiplicador
A4: Bronze | B4: 1
A5: Prata | B5: 6
A6: Ouro | B6: 18
A7: Platina | B7: 50
A8: Lendário | B8: 150
A9: Mítico | B9: 500
A10: Divino | B10: 10000
A12: Valor Semente médio (das 300 criaturas, aba 'Criaturas - Base de Dados') | B12: 31.8
A13: Fator de Escala Econômica Global | B13: 1000
A15: Fórmula de EV real ($/s esperado por carta de um pacote): EV_real = Valor Semente Médio × Fator de Escala × Σ(odds_raridade × multiplicador_raridade)
A16: Preço em $ = EV_real × Payback (segundos) — tempo de produção necessário pra 'pagar' o pacote. Quanto MENOR o payback, melhor o negócio pro jogador (pacotes de tier mais alto compensam mais rápido).
A18: Nota: fórmula assume carta recém-nascida (Grau/Despertar neutro, sem bônus de Renascimento). Serve como estimativa inicial de balanceamento — ajustar após testes em Studio.
A20: Curva de Preço Acelerada — Pacotes Gerais
A22: Preço do Pacote #1 ($) | B22: 15000000
A23: Multiplicador alvo #30 / #1 (x) | B23: 120
A24: Expoente de convexidade do preço (P) | B24: 1.8
A26: Curva de Nível Necessário — Pacotes Gerais
A28: Nível necessário no Pacote #30 (máx) | B28: 300
A29: Expoente de convexidade do nível (LP) | B29: 1.5
A31: Fórmula: Preço(N) = Preço#1 × Multiplicador ^ (((N-1)/29) ^ P). Nível(N) = 1 + ROUND((NívelMáx-1) × ((N-1)/29) ^ LP). Ambas convexas: salto pequeno no início, grande no fim. Arredondamento manual pós-fórmula (ver coluna 'Preço' na aba Catálogo — combina ROUND com steps de granularidade por faixa).

Sheet Pacotes - Catálogo
A1: ID | B1: Nome | C1: Categoria | D1: Moeda | E1: Cartas/Compra | F1: % Bronze | G1: % Prata | H1: % Ouro | I1: % Platina | J1: % Lendário | K1: % Mítico | L1: % Divino | M1: Soma Odds | N1: EV (mult. raridade) | O1: Payback (s) / Markup | P1: Preço | Q1: Notas | R1: Nível Necessário
A2: 1 | B2: Novato | C2: Geral | D2: $ | E2: 1 | F2: 0.7 | G2: 0.2 | H2: 0.07 | I2: 0.025 | J2: 0.004 | K2: 0.001 | L2: 0 | M2: =SUM(F2:L2) -> 1 | N2: =F2*'Pacotes - Parâmetros'!$B$4+G2*'Pacotes - Parâmetros'!$B$5+H2*'Pacotes - Parâmetros'!$B$6+I2*'Pacotes - Parâmetros'!$B$7+J2*'Pacotes - Parâmetros'!$B$8+K2*'Pacotes - Parâmetros'!$B$9+L2*'Pacotes - Parâmetros'!$B$10 -> 5.51 | O2: 90 | P2: =ROUND('Pacotes - Parâmetros'!$B$22*'Pacotes - Parâmetros'!$B$23^(((A2-1)/29)^'Pacotes - Parâmetros'!$B$24),-5) -> 15000000 | Q2: Ladder geral — nível 1/30 | R2: =1+ROUND(('Pacotes - Parâmetros'!$B$28-1)*(((A2-1)/29)^'Pacotes - Parâmetros'!$B$29),0) -> 1
A3: 2 | B3: Recruta | C3: Geral | D3: $ | E3: 1 | F3: 0.69138 | G3: 0.20172 | H3: 0.07276 | I3: 0.0269 | J3: 0.00559 | K3: 0.00166 | L3: 0 | M3: =SUM(F3:L3) -> 1.00001 | N3: =F3*'Pacotes - Parâmetros'!$B$4+G3*'Pacotes - Parâmetros'!$B$5+H3*'Pacotes - Parâmetros'!$B$6+I3*'Pacotes - Parâmetros'!$B$7+J3*'Pacotes - Parâmetros'!$B$8+K3*'Pacotes - Parâmetros'!$B$9+L3*'Pacotes - Parâmetros'!$B$10 -> 6.22488 | O3: 88.8 | P3: =ROUND('Pacotes - Parâmetros'!$B$22*'Pacotes - Parâmetros'!$B$23^(((A3-1)/29)^'Pacotes - Parâmetros'!$B$24),-5) -> 15200000 | Q3: Ladder geral — nível 2/30 | R3: =1+ROUND(('Pacotes - Parâmetros'!$B$28-1)*(((A3-1)/29)^'Pacotes - Parâmetros'!$B$29),0) -> 3
A4: 3 | B4: Aprendiz | C4: Geral | D4: $ | E4: 1 | F4: 0.68276 | G4: 0.20345 | H4: 0.07552 | I4: 0.02879 | J4: 0.00717 | K4: 0.00231 | L4: 0 | M4: =SUM(F4:L4) -> 1 | N4: =F4*'Pacotes - Parâmetros'!$B$4+G4*'Pacotes - Parâmetros'!$B$5+H4*'Pacotes - Parâmetros'!$B$6+I4*'Pacotes - Parâmetros'!$B$7+J4*'Pacotes - Parâmetros'!$B$8+K4*'Pacotes - Parâmetros'!$B$9+L4*'Pacotes - Parâmetros'!$B$10 -> 6.93282 | O4: 87.6 | P4: =ROUND('Pacotes - Parâmetros'!$B$22*'Pacotes - Parâmetros'!$B$23^(((A4-1)/29)^'Pacotes - Parâmetros'!$B$24),-5) -> 15600000 | Q4: Ladder geral — nível 3/30 | R4: =1+ROUND(('Pacotes - Parâmetros'!$B$28-1)*(((A4-1)/29)^'Pacotes - Parâmetros'!$B$29),0) -> 6
A5: 4 | B5: Errante | C5: Geral | D5: $ | E5: 1 | F5: 0.67414 | G5: 0.20517 | H5: 0.07828 | I5: 0.03069 | J5: 0.00876 | K5: 0.00297 | L5: 0 | M5: =SUM(F5:L5) -> 1.00001 | N5: =F5*'Pacotes - Parâmetros'!$B$4+G5*'Pacotes - Parâmetros'!$B$5+H5*'Pacotes - Parâmetros'!$B$6+I5*'Pacotes - Parâmetros'!$B$7+J5*'Pacotes - Parâmetros'!$B$8+K5*'Pacotes - Parâmetros'!$B$9+L5*'Pacotes - Parâmetros'!$B$10 -> 7.6477 | O5: 86.4 | P5: =ROUND('Pacotes - Parâmetros'!$B$22*'Pacotes - Parâmetros'!$B$23^(((A5-1)/29)^'Pacotes - Parâmetros'!$B$24),-5) -> 16300000 | Q5: Ladder geral — nível 4/30 | R5: =1+ROUND(('Pacotes - Parâmetros'!$B$28-1)*(((A5-1)/29)^'Pacotes - Parâmetros'!$B$29),0) -> 11
A6: 5 | B6: Andarilho | C6: Geral | D6: $ | E6: 1 | F6: 0.66552 | G6: 0.2069 | H6: 0.08103 | I6: 0.03259 | J6: 0.01034 | K6: 0.00362 | L6: 0 | M6: =SUM(F6:L6) -> 1 | N6: =F6*'Pacotes - Parâmetros'!$B$4+G6*'Pacotes - Parâmetros'!$B$5+H6*'Pacotes - Parâmetros'!$B$6+I6*'Pacotes - Parâmetros'!$B$7+J6*'Pacotes - Parâmetros'!$B$8+K6*'Pacotes - Parâmetros'!$B$9+L6*'Pacotes - Parâmetros'!$B$10 -> 8.35596 | O6: 85.2 | P6: =ROUND('Pacotes - Parâmetros'!$B$22*'Pacotes - Parâmetros'!$B$23^(((A6-1)/29)^'Pacotes - Parâmetros'!$B$24),-5) -> 17200000 | Q6: Ladder geral — nível 5/30 | R6: =1+ROUND(('Pacotes - Parâmetros'!$B$28-1)*(((A6-1)/29)^'Pacotes - Parâmetros'!$B$29),0) -> 16
A7: 6 | B7: Explorador | C7: Geral | D7: $ | E7: 1 | F7: 0.6569 | G7: 0.20862 | H7: 0.08379 | I7: 0.03448 | J7: 0.01193 | K7: 0.00428 | L7: 0 | M7: =SUM(F7:L7) -> 1 | N7: =F7*'Pacotes - Parâmetros'!$B$4+G7*'Pacotes - Parâmetros'!$B$5+H7*'Pacotes - Parâmetros'!$B$6+I7*'Pacotes - Parâmetros'!$B$7+J7*'Pacotes - Parâmetros'!$B$8+K7*'Pacotes - Parâmetros'!$B$9+L7*'Pacotes - Parâmetros'!$B$10 -> 9.07034 | O7: 84 | P7: =ROUND('Pacotes - Parâmetros'!$B$22*'Pacotes - Parâmetros'!$B$23^(((A7-1)/29)^'Pacotes - Parâmetros'!$B$24),-5) -> 18400000 | Q7: Ladder geral — nível 6/30 | R7: =1+ROUND(('Pacotes - Parâmetros'!$B$28-1)*(((A7-1)/29)^'Pacotes - Parâmetros'!$B$29),0) -> 22
A8: 7 | B8: Caçador | C8: Geral | D8: $ | E8: 1 | F8: 0.64828 | G8: 0.21034 | H8: 0.08655 | I8: 0.03638 | J8: 0.01352 | K8: 0.00493 | L8: 0 | M8: =SUM(F8:L8) -> 1 | N8: =F8*'Pacotes - Parâmetros'!$B$4+G8*'Pacotes - Parâmetros'!$B$5+H8*'Pacotes - Parâmetros'!$B$6+I8*'Pacotes - Parâmetros'!$B$7+J8*'Pacotes - Parâmetros'!$B$8+K8*'Pacotes - Parâmetros'!$B$9+L8*'Pacotes - Parâmetros'!$B$10 -> 9.78022 | O8: 82.8 | P8: =ROUND('Pacotes - Parâmetros'!$B$22*'Pacotes - Parâmetros'!$B$23^(((A8-1)/29)^'Pacotes - Parâmetros'!$B$24),-5) -> 19900000 | Q8: Ladder geral — nível 7/30 | R8: =1+ROUND(('Pacotes - Parâmetros'!$B$28-1)*(((A8-1)/29)^'Pacotes - Parâmetros'!$B$29),0) -> 29
A9: 8 | B9: Rastreador | C9: Geral | D9: $ | E9: 1 | F9: 0.63966 | G9: 0.21207 | H9: 0.08931 | I9: 0.03828 | J9: 0.0151 | K9: 0.00559 | L9: 0 | M9: =SUM(F9:L9) -> 1.00001 | N9: =F9*'Pacotes - Parâmetros'!$B$4+G9*'Pacotes - Parâmetros'!$B$5+H9*'Pacotes - Parâmetros'!$B$6+I9*'Pacotes - Parâmetros'!$B$7+J9*'Pacotes - Parâmetros'!$B$8+K9*'Pacotes - Parâmetros'!$B$9+L9*'Pacotes - Parâmetros'!$B$10 -> 10.49366 | O9: 81.6 | P9: =ROUND('Pacotes - Parâmetros'!$B$22*'Pacotes - Parâmetros'!$B$23^(((A9-1)/29)^'Pacotes - Parâmetros'!$B$24),-5) -> 21700000 | Q9: Ladder geral — nível 8/30 | R9: =1+ROUND(('Pacotes - Parâmetros'!$B$28-1)*(((A9-1)/29)^'Pacotes - Parâmetros'!$B$29),0) -> 36
A10: 9 | B10: Guerreiro | C10: Geral | D10: $ | E10: 1 | F10: 0.63103 | G10: 0.21379 | H10: 0.09207 | I10: 0.04017 | J10: 0.01669 | K10: 0.00624 | L10: 0 | M10: =SUM(F10:L10) -> 0.99999 | N10: =F10*'Pacotes - Parâmetros'!$B$4+G10*'Pacotes - Parâmetros'!$B$5+H10*'Pacotes - Parâmetros'!$B$6+I10*'Pacotes - Parâmetros'!$B$7+J10*'Pacotes - Parâmetros'!$B$8+K10*'Pacotes - Parâmetros'!$B$9+L10*'Pacotes - Parâmetros'!$B$10 -> 11.20303 | O10: 80.3 | P10: =ROUND('Pacotes - Parâmetros'!$B$22*'Pacotes - Parâmetros'!$B$23^(((A10-1)/29)^'Pacotes - Parâmetros'!$B$24),-5) -> 24000000 | Q10: Ladder geral — nível 9/30 | R10: =1+ROUND(('Pacotes - Parâmetros'!$B$28-1)*(((A10-1)/29)^'Pacotes - Parâmetros'!$B$29),0) -> 44
A11: 10 | B11: Bravo | C11: Geral | D11: $ | E11: 1 | F11: 0.62241 | G11: 0.21552 | H11: 0.09483 | I11: 0.04207 | J11: 0.01828 | K11: 0.0069 | L11: 0 | M11: =SUM(F11:L11) -> 1.00001 | N11: =F11*'Pacotes - Parâmetros'!$B$4+G11*'Pacotes - Parâmetros'!$B$5+H11*'Pacotes - Parâmetros'!$B$6+I11*'Pacotes - Parâmetros'!$B$7+J11*'Pacotes - Parâmetros'!$B$8+K11*'Pacotes - Parâmetros'!$B$9+L11*'Pacotes - Parâmetros'!$B$10 -> 11.91797 | O11: 79.1 | P11: =ROUND('Pacotes - Parâmetros'!$B$22*'Pacotes - Parâmetros'!$B$23^(((A11-1)/29)^'Pacotes - Parâmetros'!$B$24),-5) -> 26900000 | Q11: Ladder geral — nível 10/30 | R11: =1+ROUND(('Pacotes - Parâmetros'!$B$28-1)*(((A11-1)/29)^'Pacotes - Parâmetros'!$B$29),0) -> 53
A12: 11 | B12: Guardião | C12: Geral | D12: $ | E12: 1 | F12: 0.61379 | G12: 0.21724 | H12: 0.09759 | I12: 0.04397 | J12: 0.01986 | K12: 0.00755 | L12: 0 | M12: =SUM(F12:L12) -> 1 | N12: =F12*'Pacotes - Parâmetros'!$B$4+G12*'Pacotes - Parâmetros'!$B$5+H12*'Pacotes - Parâmetros'!$B$6+I12*'Pacotes - Parâmetros'!$B$7+J12*'Pacotes - Parâmetros'!$B$8+K12*'Pacotes - Parâmetros'!$B$9+L12*'Pacotes - Parâmetros'!$B$10 -> 12.62635 | O12: 77.9 | P12: =ROUND('Pacotes - Parâmetros'!$B$22*'Pacotes - Parâmetros'!$B$23^(((A12-1)/29)^'Pacotes - Parâmetros'!$B$24),-5) -> 30300000 | Q12: Ladder geral — nível 11/30 | R12: =1+ROUND(('Pacotes - Parâmetros'!$B$28-1)*(((A12-1)/29)^'Pacotes - Parâmetros'!$B$29),0) -> 62
A13: 12 | B13: Sentinela | C13: Geral | D13: $ | E13: 1 | F13: 0.60517 | G13: 0.21897 | H13: 0.10034 | I13: 0.04586 | J13: 0.02145 | K13: 0.00821 | L13: 0 | M13: =SUM(F13:L13) -> 1 | N13: =F13*'Pacotes - Parâmetros'!$B$4+G13*'Pacotes - Parâmetros'!$B$5+H13*'Pacotes - Parâmetros'!$B$6+I13*'Pacotes - Parâmetros'!$B$7+J13*'Pacotes - Parâmetros'!$B$8+K13*'Pacotes - Parâmetros'!$B$9+L13*'Pacotes - Parâmetros'!$B$10 -> 13.34061 | O13: 76.7 | P13: =ROUND('Pacotes - Parâmetros'!$B$22*'Pacotes - Parâmetros'!$B$23^(((A13-1)/29)^'Pacotes - Parâmetros'!$B$24),-5) -> 34600000 | Q13: Ladder geral — nível 12/30 | R13: =1+ROUND(('Pacotes - Parâmetros'!$B$28-1)*(((A13-1)/29)^'Pacotes - Parâmetros'!$B$29),0) -> 71
... A31: 30 | B31: Transcendente | C31: Geral | D31: $ | E31: 1 | F31: 0.45 | G31: 0.25 | H31: 0.15 | I31: 0.08 | J31: 0.05 | K31: 0.02 | L31: 0 | M31: =SUM(F31:L31) -> 1 | N31: =F31*'Pacotes - Parâmetros'!$B$4+G31*'Pacotes - Parâmetros'!$B$5+H31*'Pacotes - Parâmetros'!$B$6+I31*'Pacotes - Parâmetros'!$B$7+J31*'Pacotes - Parâmetros'!$B$8+K31*'Pacotes - Parâmetros'!$B$9+L31*'Pacotes - Parâmetros'!$B$10 -> 26.15 | O31: 55 | P31: =ROUND('Pacotes - Parâmetros'!$B$22*'Pacotes - Parâmetros'!$B$23^(((A31-1)/29)^'Pacotes - Parâmetros'!$B$24),-5) -> 1800000000 | Q31: Ladder geral — nível 30/30 | R31: =1+ROUND(('Pacotes - Parâmetros'!$B$28-1)*(((A31-1)/29)^'Pacotes - Parâmetros'!$B$29),0) -> 300
A32: 31 | B32: Fragmento de Diamante | C32: Diamante | D32: 💎 | E32: 1 | F32: 0.42 | G32: 0.24 | H32: 0.16 | I32: 0.095 | J32: 0.06 | K32: 0.025 | L32: 0 | M32: =SUM(F32:L32) -> 1 | N32: =F32*'Pacotes - Parâmetros'!$B$4+G32*'Pacotes - Parâmetros'!$B$5+H32*'Pacotes - Parâmetros'!$B$6+I32*'Pacotes - Parâmetros'!$B$7+J32*'Pacotes - Parâmetros'!$B$8+K32*'Pacotes - Parâmetros'!$B$9+L32*'Pacotes - Parâmetros'!$B$10 -> 30.99 | O32: 50 | P32: =ROUND(N32*O32,-1) -> 1550 | Q32: Ladder diamante — nível 1/6 | Preço em 💎 ainda é estimativa abstrata — depende de como o jogador vai gerar Diamante.
A33: 32 | B33: Cristal de Diamante | C33: Diamante | D33: 💎 | E33: 1 | F33: 0.396 | G33: 0.236 | H33: 0.164 | I33: 0.106 | J33: 0.068 | K33: 0.03 | L33: 0 | M33: =SUM(F33:L33) -> 1 | N33: =F33*'Pacotes - Parâmetros'!$B$4+G33*'Pacotes - Parâmetros'!$B$5+H33*'Pacotes - Parâmetros'!$B$6+I33*'Pacotes - Parâmetros'!$B$7+J33*'Pacotes - Parâmetros'!$B$8+K33*'Pacotes - Parâmetros'!$B$9+L33*'Pacotes - Parâmetros'!$B$10 -> 35.264 | O33: 47 | P33: =ROUND(N33*O33,-1) -> 1660 | Q33: Ladder diamante — nível 2/6 | Preço em 💎 ainda é estimativa abstrata — depende de como o jogador vai gerar Diamante.
A34: 33 | B34: Núcleo de Diamante | C34: Diamante | D34: 💎 | E34: 1 | F34: 0.372 | G34: 0.232 | H34: 0.168 | I34: 0.117 | J34: 0.076 | K34: 0.035 | L34: 0 | M34: =SUM(F34:L34) -> 1 | N34: =F34*'Pacotes - Parâmetros'!$B$4+G34*'Pacotes - Parâmetros'!$B$5+H34*'Pacotes - Parâmetros'!$B$6+I34*'Pacotes - Parâmetros'!$B$7+J34*'Pacotes - Parâmetros'!$B$8+K34*'Pacotes - Parâmetros'!$B$9+L34*'Pacotes - Parâmetros'!$B$10 -> 39.538 | O34: 44 | P34: =ROUND(N34*O34,-1) -> 1740 | Q34: Ladder diamante — nível 3/6 | Preço em 💎 ainda é estimativa abstrata — depende de como o jogador vai gerar Diamante.
A35: 34 | B35: Prisma de Diamante | C35: Diamante | D35: 💎 | E35: 1 | F35: 0.348 | G35: 0.228 | H35: 0.172 | I35: 0.128 | J35: 0.084 | K35: 0.04 | L35: 0 | M35: =SUM(F35:L35) -> 1 | N35: =F35*'Pacotes - Parâmetros'!$B$4+G35*'Pacotes - Parâmetros'!$B$5+H35*'Pacotes - Parâmetros'!$B$6+I35*'Pacotes - Parâmetros'!$B$7+J35*'Pacotes - Parâmetros'!$B$8+K35*'Pacotes - Parâmetros'!$B$9+L35*'Pacotes - Parâmetros'!$B$10 -> 43.812 | O35: 41 | P35: =ROUND(N35*O35,-1) -> 1800 | Q35: Ladder diamante — nível 4/6 | Preço em 💎 ainda é estimativa abstrata — depende de como o jogador vai gerar Diamante.
A36: 35 | B36: Coroa de Diamante | C36: Diamante | D36: 💎 | E36: 1 | F36: 0.324 | G36: 0.224 | H36: 0.176 | I36: 0.139 | J36: 0.092 | K36: 0.045 | L36: 0 | M36: =SUM(F36:L36) -> 1 | N36: =F36*'Pacotes - Parâmetros'!$B$4+G36*'Pacotes - Parâmetros'!$B$5+H36*'Pacotes - Parâmetros'!$B$6+I36*'Pacotes - Parâmetros'!$B$7+J36*'Pacotes - Parâmetros'!$B$8+K36*'Pacotes - Parâmetros'!$B$9+L36*'Pacotes - Parâmetros'!$B$10 -> 48.086 | O36: 38 | P36: =ROUND(N36*O36,-1) -> 1830 | Q36: Ladder diamante — nível 5/6 | Preço em 💎 ainda é estimativa abstrata — depende de como o jogador vai gerar Diamante.
A37: 36 | B37: Ápice de Diamante | C37: Diamante | D37: 💎 | E37: 1 | F37: 0.3 | G37: 0.22 | H37: 0.18 | I37: 0.15 | J37: 0.1 | K37: 0.05 | L37: 0 | M37: =SUM(F37:L37) -> 1 | N37: =F37*'Pacotes - Parâmetros'!$B$4+G37*'Pacotes - Parâmetros'!$B$5+H37*'Pacotes - Parâmetros'!$B$6+I37*'Pacotes - Parâmetros'!$B$7+J37*'Pacotes - Parâmetros'!$B$8+K37*'Pacotes - Parâmetros'!$B$9+L37*'Pacotes - Parâmetros'!$B$10 -> 52.36 | O37: 35 | P37: =ROUND(N37*O37,-1) -> 1830 | Q37: Ladder diamante — nível 6/6 | Preço em 💎 ainda é estimativa abstrata — depende de como o jogador vai gerar Diamante.
A38: 37 | B38: Escudeiro | C38: Robux | D38: Robux | E38: 1 | F38: 0.28 | G38: 0.22 | H38: 0.19 | I38: 0.16 | J38: 0.11 | K38: 0.04 | L38: 0 | M38: =SUM(F38:L38) -> 1 | N38: =F38*'Pacotes - Parâmetros'!$B$4+G38*'Pacotes - Parâmetros'!$B$5+H38*'Pacotes - Parâmetros'!$B$6+I38*'Pacotes - Parâmetros'!$B$7+J38*'Pacotes - Parâmetros'!$B$8+K38*'Pacotes - Parâmetros'!$B$9+L38*'Pacotes - Parâmetros'!$B$10 -> 49.52 | O38: 45 | P38: 99 | Q38: Ladder Robux — nível 1/9
A39: 38 | B39: Nobre | C39: Robux | D39: Robux | E39: 1 | F39: 0.2575 | G39: 0.21125 | H39: 0.19125 | I39: 0.17125 | J39: 0.12125 | K39: 0.0475 | L39: 0 | M39: =SUM(F39:L39) -> 1 | N39: =F39*'Pacotes - Parâmetros'!$B$4+G39*'Pacotes - Parâmetros'!$B$5+H39*'Pacotes - Parâmetros'!$B$6+I39*'Pacotes - Parâmetros'!$B$7+J39*'Pacotes - Parâmetros'!$B$8+K39*'Pacotes - Parâmetros'!$B$9+L39*'Pacotes - Parâmetros'!$B$10 -> 55.4675 | O39: 43.1 | P39: 149 | Q39: Ladder Robux — nível 2/9
A40: 39 | B40: Duque | C40: Robux | D40: Robux | E40: 1 | F40: 0.235 | G40: 0.2025 | H40: 0.1925 | I40: 0.1825 | J40: 0.1325 | K40: 0.055 | L40: 0 | M40: =SUM(F40:L40) -> 1 | N40: =F40*'Pacotes - Parâmetros'!$B$4+G40*'Pacotes - Parâmetros'!$B$5+H40*'Pacotes - Parâmetros'!$B$6+I40*'Pacotes - Parâmetros'!$B$7+J40*'Pacotes - Parâmetros'!$B$8+K40*'Pacotes - Parâmetros'!$B$9+L40*'Pacotes - Parâmetros'!$B$10 -> 61.415 | O40: 41.2 | P40: 249 | Q40: Ladder Robux — nível 3/9
A41: 40 | B41: Monarca | C41: Robux | D41: Robux | E41: 1 | F41: 0.2125 | G41: 0.19375 | H41: 0.19375 | I41: 0.19375 | J41: 0.14375 | K41: 0.0625 | L41: 0 | M41: =SUM(F41:L41) -> 1 | N41: =F41*'Pacotes - Parâmetros'!$B$4+G41*'Pacotes - Parâmetros'!$B$5+H41*'Pacotes - Parâmetros'!$B$6+I41*'Pacotes - Parâmetros'!$B$7+J41*'Pacotes - Parâmetros'!$B$8+K41*'Pacotes - Parâmetros'!$B$9+L41*'Pacotes - Parâmetros'!$B$10 -> 67.3625 | O41: 39.4 | P41: 399 | Q41: Ladder Robux — nível 4/9
A42: 41 | B42: Soberano | C42: Robux | D42: Robux | E42: 1 | F42: 0.19 | G42: 0.185 | H42: 0.195 | I42: 0.205 | J42: 0.155 | K42: 0.07 | L42: 0 | M42: =SUM(F42:L42) -> 1 | N42: =F42*'Pacotes - Parâmetros'!$B$4+G42*'Pacotes - Parâmetros'!$B$5+H42*'Pacotes - Parâmetros'!$B$6+I42*'Pacotes - Parâmetros'!$B$7+J42*'Pacotes - Parâmetros'!$B$8+K42*'Pacotes - Parâmetros'!$B$9+L42*'Pacotes - Parâmetros'!$B$10 -> 73.31 | O42: 37.5 | P42: 649 | Q42: Ladder Robux — nível 5/9
A43: 42 | B43: Imperador | C43: Robux | D43: Robux | E43: 1 | F43: 0.1675 | G43: 0.17625 | H43: 0.19625 | I43: 0.21625 | J43: 0.16625 | K43: 0.0775 | L43: 0 | M43: =SUM(F43:L43) -> 1 | N43: =F43*'Pacotes - Parâmetros'!$B$4+G43*'Pacotes - Parâmetros'!$B$5+H43*'Pacotes - Parâmetros'!$B$6+I43*'Pacotes - Parâmetros'!$B$7+J43*'Pacotes - Parâmetros'!$B$8+K43*'Pacotes - Parâmetros'!$B$9+L43*'Pacotes - Parâmetros'!$B$10 -> 79.2575 | O43: 35.6 | P43: 999 | Q43: Ladder Robux — nível 6/9
A44: 43 | B44: Baú do Colecionador | C44: Robux | D44: Robux | E44: 3 | F44: 0.145 | G44: 0.1675 | H44: 0.1975 | I44: 0.2275 | J44: 0.1775 | K44: 0.085 | L44: 0 | M44: =SUM(F44:L44) -> 1 | N44: =F44*'Pacotes - Parâmetros'!$B$4+G44*'Pacotes - Parâmetros'!$B$5+H44*'Pacotes - Parâmetros'!$B$6+I44*'Pacotes - Parâmetros'!$B$7+J44*'Pacotes - Parâmetros'!$B$8+K44*'Pacotes - Parâmetros'!$B$9+L44*'Pacotes - Parâmetros'!$B$10 -> 85.205 | O44: 33.8 | P44: 349 | Q44: Multi-carta (3 cartas por compra) — nível 7/9
A45: 44 | B45: Baú do Patrono | C45: Robux | D45: Robux | E45: 5 | F45: 0.1225 | G45: 0.15875 | H45: 0.19875 | I45: 0.23875 | J45: 0.18875 | K45: 0.0925 | L45: 0 | M45: =SUM(F45:L45) -> 1 | N45: =F45*'Pacotes - Parâmetros'!$B$4+G45*'Pacotes - Parâmetros'!$B$5+H45*'Pacotes - Parâmetros'!$B$6+I45*'Pacotes - Parâmetros'!$B$7+J45*'Pacotes - Parâmetros'!$B$8+K45*'Pacotes - Parâmetros'!$B$9+L45*'Pacotes - Parâmetros'!$B$10 -> 91.1525 | O45: 31.9 | P45: 799 | Q45: Multi-carta (5 cartas por compra) — nível 8/9
A46: 45 | B46: Baú do Fundador | C46: Robux | D46: Robux | E46: 8 | F46: 0.1 | G46: 0.15 | H46: 0.2 | I46: 0.25 | J46: 0.2 | K46: 0.1 | L46: 0 | M46: =SUM(F46:L46) -> 1 | N46: =F46*'Pacotes - Parâmetros'!$B$4+G46*'Pacotes - Parâmetros'!$B$5+H46*'Pacotes - Parâmetros'!$B$6+I46*'Pacotes - Parâmetros'!$B$7+J46*'Pacotes - Parâmetros'!$B$8+K46*'Pacotes - Parâmetros'!$B$9+L46*'Pacotes - Parâmetros'!$B$10 -> 97.1 | O46: 30 | P46: 1499 | Q46: Multi-carta (8 cartas por compra) — nível 9/9
A47: 46 | B47: Chegada | C47: Especial/Evento | D47: Grátis | E47: 1 | F47: 0.4 | G47: 0.3 | H47: 0.2 | I47: 0.08 | J47: 0.02 | K47: 0 | L47: 0 | M47: =SUM(F47:L47) -> 1 | N47: =F47*'Pacotes - Parâmetros'!$B$4+G47*'Pacotes - Parâmetros'!$B$5+H47*'Pacotes - Parâmetros'!$B$6+I47*'Pacotes - Parâmetros'!$B$7+J47*'Pacotes - Parâmetros'!$B$8+K47*'Pacotes - Parâmetros'!$B$9+L47*'Pacotes - Parâmetros'!$B$10 -> 12.8 | P47: Grátis | Q47: Starter — 1x por conta nova
A48: 47 | B48: Bênção Diária | C48: Especial/Evento | D48: Grátis | E48: 1 | F48: 0.8 | G48: 0.15 | H48: 0.04 | I48: 0.009 | J48: 0.001 | K48: 0 | L48: 0 | M48: =SUM(F48:L48) -> 1 | N48: =F48*'Pacotes - Parâmetros'!$B$4+G48*'Pacotes - Parâmetros'!$B$5+H48*'Pacotes - Parâmetros'!$B$6+I48*'Pacotes - Parâmetros'!$B$7+J48*'Pacotes - Parâmetros'!$B$8+K48*'Pacotes - Parâmetros'!$B$9+L48*'Pacotes - Parâmetros'!$B$10 -> 3.02 | P48: Grátis | Q48: Grátis, 1x por dia
A49: 48 | B49: Retorno do Herói | C49: Especial/Evento | D49: Grátis | E49: 1 | F49: 0.3 | G49: 0.3 | H49: 0.25 | I49: 0.1 | J49: 0.04 | K49: 0.01 | L49: 0 | M49: =SUM(F49:L49) -> 1 | N49: =F49*'Pacotes - Parâmetros'!$B$4+G49*'Pacotes - Parâmetros'!$B$5+H49*'Pacotes - Parâmetros'!$B$6+I49*'Pacotes - Parâmetros'!$B$7+J49*'Pacotes - Parâmetros'!$B$8+K49*'Pacotes - Parâmetros'!$B$9+L49*'Pacotes - Parâmetros'!$B$10 -> 22.6 | P49: Grátis | Q49: Reengajamento — condicional
A50: 49 | B50: Relâmpago | C50: Especial/Evento | D50: $ ou 💎 (a definir) | E50: 1 | F50: 0.55 | G50: 0.24 | H50: 0.12 | I50: 0.06 | J50: 0.025 | K50: 0.005 | L50: 0 | M50: =SUM(F50:L50) -> 1 | N50: =F50*'Pacotes - Parâmetros'!$B$4+G50*'Pacotes - Parâmetros'!$B$5+H50*'Pacotes - Parâmetros'!$B$6+I50*'Pacotes - Parâmetros'!$B$7+J50*'Pacotes - Parâmetros'!$B$8+K50*'Pacotes - Parâmetros'!$B$9+L50*'Pacotes - Parâmetros'!$B$10 -> 13.4 | P50: a definir | Q50: Venda-relâmpago — janela de tempo limitada, preço com desconto vs. equivalente
A51: 50 | B51: Sorte do Destino | C51: Especial/Evento | D51: $ ou 💎 (a definir) | E51: 1 | F51: 0.2 | G51: 0.2 | H51: 0.2 | I51: 0.2 | J51: 0.15 | K51: 0.05 | L51: 0 | M51: =SUM(F51:L51) -> 1 | N51: =F51*'Pacotes - Parâmetros'!$B$4+G51*'Pacotes - Parâmetros'!$B$5+H51*'Pacotes - Parâmetros'!$B$6+I51*'Pacotes - Parâmetros'!$B$7+J51*'Pacotes - Parâmetros'!$B$8+K51*'Pacotes - Parâmetros'!$B$9+L51*'Pacotes - Parâmetros'!$B$10 -> 62.5 | P51: a definir | Q51: Evento live — odds turbinadas temporariamente
A52: 51 | B52: Primeiro Renascimento | C52: Especial/Evento | D52: Grátis | E52: 1 | F52: 0.25 | G52: 0.25 | H52: 0.25 | I52: 0.15 | J52: 0.08 | K52: 0.02 | L52: 0 | M52: =SUM(F52:L52) -> 1 | N52: =F52*'Pacotes - Parâmetros'!$B$4+G52*'Pacotes - Parâmetros'!$B$5+H52*'Pacotes - Parâmetros'!$B$6+I52*'Pacotes - Parâmetros'!$B$7+J52*'Pacotes - Parâmetros'!$B$8+K52*'Pacotes - Parâmetros'!$B$9+L52*'Pacotes - Parâmetros'!$B$10 -> 35.75 | P52: Grátis | Q52: Dado automaticamente no 1º prestígio
A53: 52 | B53: Portal Divino | C53: Especial/Evento | D53: Evento (a definir) | E53: 1 | F53: 0 | G53: 0 | H53: 0 | I53: 0 | J53: 0 | K53: 0 | L53: 1 | M53: =SUM(F53:L53) -> 1 | N53: =F53*'Pacotes - Parâmetros'!$B$4+G53*'Pacotes - Parâmetros'!$B$5+H53*'Pacotes - Parâmetros'!$B$6+I53*'Pacotes - Parâmetros'!$B$7+J53*'Pacotes - Parâmetros'!$B$8+K53*'Pacotes - Parâmetros'!$B$9+L53*'Pacotes - Parâmetros'!$B$10 -> 10000 | P53: a definir | Q53: ÚNICA fonte de Raridade Divino — garante 1 carta Divino (clã aleatório), sem fusão
A54: 53 | B54: Confluência Mística | C54: Especial/Evento | D54: $ ou 💎 (a definir) | E54: 3 | F54: 0.4 | G54: 0.25 | H54: 0.18 | I54: 0.1 | J54: 0.05 | K54: 0.02 | L54: 0 | M54: =SUM(F54:L54) -> 1 | N54: =F54*'Pacotes - Parâmetros'!$B$4+G54*'Pacotes - Parâmetros'!$B$5+H54*'Pacotes - Parâmetros'!$B$6+I54*'Pacotes - Parâmetros'!$B$7+J54*'Pacotes - Parâmetros'!$B$8+K54*'Pacotes - Parâmetros'!$B$9+L54*'Pacotes - Parâmetros'!$B$10 -> 27.64 | P54: a definir | Q54: Bundle — 3 cartas por compra
A55: 54 | B55: Aniversário | C55: Especial/Evento | D55: Grátis / Promo | E55: 1 | F55: 0.3 | G55: 0.25 | H55: 0.2 | I55: 0.15 | J55: 0.08 | K55: 0.02 | L55: 0 | M55: =SUM(F55:L55) -> 1 | N55: =F55*'Pacotes - Parâmetros'!$B$4+G55*'Pacotes - Parâmetros'!$B$5+H55*'Pacotes - Parâmetros'!$B$6+I55*'Pacotes - Parâmetros'!$B$7+J55*'Pacotes - Parâmetros'!$B$8+K55*'Pacotes - Parâmetros'!$B$9+L55*'Pacotes - Parâmetros'!$B$10 -> 34.9 | P55: Grátis | Q55: Evento anual — data de aniversário do jogo
A56: 55 | B56: Solstício de Verão | C56: Especial/Evento | D56: Promo (a definir) | E56: 1 | F56: 0.35 | G56: 0.28 | H56: 0.2 | I56: 0.12 | J56: 0.04 | K56: 0.01 | L56: 0 | M56: =SUM(F56:L56) -> 1 | N56: =F56*'Pacotes - Parâmetros'!$B$4+G56*'Pacotes - Parâmetros'!$B$5+H56*'Pacotes - Parâmetros'!$B$6+I56*'Pacotes - Parâmetros'!$B$7+J56*'Pacotes - Parâmetros'!$B$8+K56*'Pacotes - Parâmetros'!$B$9+L56*'Pacotes - Parâmetros'!$B$10 -> 22.63 | P56: a definir | Q56: Sazonal — verão
A57: 56 | B57: Noite das Sombras | C57: Especial/Evento | D57: Promo (a definir) | E57: 1 | F57: 0.35 | G57: 0.27 | H57: 0.2 | I57: 0.12 | J57: 0.05 | K57: 0.01 | L57: 0 | M57: =SUM(F57:L57) -> 1 | N57: =F57*'Pacotes - Parâmetros'!$B$4+G57*'Pacotes - Parâmetros'!$B$5+H57*'Pacotes - Parâmetros'!$B$6+I57*'Pacotes - Parâmetros'!$B$7+J57*'Pacotes - Parâmetros'!$B$8+K57*'Pacotes - Parâmetros'!$B$9+L57*'Pacotes - Parâmetros'!$B$10 -> 24.07 | P57: a definir | Q57: Sazonal — outubro
A58: 57 | B58: Amanhecer de Ano Novo | C58: Especial/Evento | D58: Promo (a definir) | E58: 1 | F58: 0.32 | G58: 0.28 | H58: 0.2 | I58: 0.13 | J58: 0.06 | K58: 0.01 | L58: 0 | M58: =SUM(F58:L58) -> 1 | N58: =F58*'Pacotes - Parâmetros'!$B$4+G58*'Pacotes - Parâmetros'!$B$5+H58*'Pacotes - Parâmetros'!$B$6+I58*'Pacotes - Parâmetros'!$B$7+J58*'Pacotes - Parâmetros'!$B$8+K58*'Pacotes - Parâmetros'!$B$9+L58*'Pacotes - Parâmetros'!$B$10 -> 26.1 | P58: a definir | Q58: Sazonal — virada de ano
... A63: 62 | B63: Festival da Primavera | C63: Especial/Evento | D63: Promo (a definir) | E63: 1 | F63: 0.35 | G63: 0.27 | H63: 0.2 | I63: 0.12 | J63: 0.05 | K63: 0.01 | L63: 0 | M63: =SUM(F63:L63) -> 1 | N63: =F63*'Pacotes - Parâmetros'!$B$4+G63*'Pacotes - Parâmetros'!$B$5+H63*'Pacotes - Parâmetros'!$B$6+I63*'Pacotes - Parâmetros'!$B$7+J63*'Pacotes - Parâmetros'!$B$8+K63*'Pacotes - Parâmetros'!$B$9+L63*'Pacotes - Parâmetros'!$B$10 -> 24.07 | P63: a definir | Q63: Sazonal — primavera

Sheet Metadata
A1: 🔍 METADATA — Auditoria da Planilha Cartas Míticas
A2: Gerado em | B2: Julho 19, 2026 | C2: Status: ✅ Completo e Validado
A4: RESUMO DE CONTEÚDO
A5: Clãs Totais | B5: 15 | C5: Ordem Celestial até Engrenagem Rúnica
A6: Criaturas Base | B6: 300 | C6: 20 por clã × 15 clãs
A7: Criaturas Divinas | B7: 15 | C7: 1 por clã (Evento/Robux exclusivo)
A8: Raridades Padrão | B8: 7 | C8: Default, Bronze, Prata, Ouro, Platina, Lendário, Mítico
A9: Raridade Especial | B9: 1 | C9: Divino (×10.000 multiplicador, sem evolução por acúmulo)
A10: Pacotes Totais | B10: 62 | C10: 30 Geral + 6 Diamante + 9 Robux + 17 Especial/Evento
A11: Sistema de Grau | B11: 7 | C11: Vazio (padrão) + 7.0 até 10.0 em intervalos de 0.5
A12: Combinações Possíveis | B12: 1.800 | C12: 300 criaturas × 6 raridades (Divino não entra = +15)
A14: CHECKPOINTS FINAIS | B14: ✅ STATUS | C14: NOTA
A15: Cores dos Clãs (15) | B15: ✅ | C15: Sem espaços extras, validadas contra Midjourney
A16: Criaturas Divinas (15) | B16: ✅ | C16: Completas, mitologia de domínio público
A17: Sistema de Raridade | B17: ✅ | C17: Default multiplicador ajustado, 7 raridades + 1 especial
A18: Pacotes Catálogo (62) | B18: ✅ | C18: Odds de rarity definidas, preços/moedas validadas
A19: Matriz Completa (1.800) | B19: ✅ | C19: Fórmulas formuladas, valores calculados por rarity × multiplier
A20: UI Style Guide | B20: ✅ | C20: Paleta, tipografia, componentes, animações documentadas
A21: Sistema de Despertar | B21: ✅ | C21: 7 graus (vazio + 7.0-10.0), multiplicadores 1.05-2.5
A23: PRÓXIMOS PASSOS
A24: 1. Testar em Roblox Studio | B24: Validar valores em jogo, verificar animação Divino border
A25: 2. Criar Divino Event Pack | B25: Implementar sistema de abertura exclusiva, congelamento de raridade
A26: 3. Prototipar Telas UI | B26: HTML mockups → React component hierarquia para Roblox
A27: 4. Balance Playtest | B27: 150 packs/dia simulado, curva de progressão validada

Sheet Pacotes - Legenda
A1: Como usar as abas de Pacotes
A3: • 'Pacotes - Parâmetros': multiplicador por raridade + Valor Semente médio (300 criaturas) + fator de escala econômica. Editável (células azuis/amarelas).
A4: • 'Pacotes - Catálogo': os 60 pacotes definidos (30 Gerais, 6 Diamante, 9 Robux, 15 Especiais/Eventos), com odds, EV e preço.
A5: • Categoria Geral ($): preço calculado com fórmula real = Valor Semente Médio × Fator de Escala (1000) × EV (mult. raridade) × Payback em segundos.
A6: • Categoria Diamante (💎): preço ainda é uma estimativa abstrata (EV × markup) — falta decidir como o jogador gera Diamante pra amarrar isso numa fórmula real.
A7: • Categoria Robux: preços são valores fixos típicos de Developer Product do Roblox (não usam fórmula — é decisão de monetização, não de economia interna).
A8: • Categoria Especiais/Eventos: a maioria é grátis ou tem moeda/preço 'a definir' — ligado a liveops, não a uma fórmula fixa.
A9: • Todos os pacotes sorteiam entre os 15 clãs de forma uniforme. A única fonte de Raridade Divino é o pacote 'Portal Divino' (evento) — 100% garantido.
A11: Pendências antes de implementar no PackCatalog.lua:
A12: - Validar os preços em $ da categoria Geral contra a curva de ganho real de EconomyService/LevelService (jogador consegue gerar esse tanto de $ na hora certa da progressão?).
A13: - Definir como o jogador ganha 💎 Diamante p/ decidir se o preço da categoria Diamante faz sentido.
A14: - Confirmar os preços em Robux com base no público-alvo/benchmark de jogos similares.
A15: - Definir moeda e preço exatos dos pacotes de Especiais/Eventos marcados 'a definir'.
