Workbook

Sheet Parâmetros
A1: Multiplicador de Valor por Raridade (fonte: aba Sistema de Raridade e Evolução)
A3: Raridade | B3: Multiplicador
A4: Bronze | B4: 1
A5: Prata | B5: 6
A6: Ouro | B6: 18
A7: Platina | B7: 50
A8: Lendário | B8: 150
A9: Mítico | B9: 500
A10: Divino | B10: 10000
A12: Nota: valores em amarelo/azul são inputs editáveis. Mudar aqui recalcula o EV e o Preço de todos os 60 pacotes na aba Catálogo de Pacotes.

Sheet Catálogo de Pacotes
A1: ID | B1: Nome | C1: Categoria | D1: Moeda | E1: Cartas/Compra | F1: % Bronze | G1: % Prata | H1: % Ouro | I1: % Platina | J1: % Lendário | K1: % Mítico | L1: % Divino | M1: Soma Odds | N1: EV (unid. valor) | O1: Markup (x) | P1: Preço | Q1: Notas
A2: 1 | B2: Novato | C2: Geral | D2: $ | E2: 1 | F2: 0.7 | G2: 0.2 | H2: 0.07 | I2: 0.025 | J2: 0.004 | K2: 0.001 | L2: 0 | M2: =SUM(F2:L2) -> 1 | N2: =F2*Parâmetros!$B$4+G2*Parâmetros!$B$5+H2*Parâmetros!$B$6+I2*Parâmetros!$B$7+J2*Parâmetros!$B$8+K2*Parâmetros!$B$9+L2*Parâmetros!$B$10 -> 5.51 | O2: 90 | P2: =ROUND(N2*O2,-1) -> 500 | Q2: Ladder geral — nível 1/30
A3: 2 | B3: Recruta | C3: Geral | D3: $ | E3: 1 | F3: 0.69138 | G3: 0.20172 | H3: 0.07276 | I3: 0.0269 | J3: 0.00559 | K3: 0.00166 | L3: 0 | M3: =SUM(F3:L3) -> 1.00001 | N3: =F3*Parâmetros!$B$4+G3*Parâmetros!$B$5+H3*Parâmetros!$B$6+I3*Parâmetros!$B$7+J3*Parâmetros!$B$8+K3*Parâmetros!$B$9+L3*Parâmetros!$B$10 -> 6.22488 | O3: 88.8 | P3: =ROUND(N3*O3,-1) -> 550 | Q3: Ladder geral — nível 2/30
A4: 3 | B4: Aprendiz | C4: Geral | D4: $ | E4: 1 | F4: 0.68276 | G4: 0.20345 | H4: 0.07552 | I4: 0.02879 | J4: 0.00717 | K4: 0.00231 | L4: 0 | M4: =SUM(F4:L4) -> 1 | N4: =F4*Parâmetros!$B$4+G4*Parâmetros!$B$5+H4*Parâmetros!$B$6+I4*Parâmetros!$B$7+J4*Parâmetros!$B$8+K4*Parâmetros!$B$9+L4*Parâmetros!$B$10 -> 6.93282 | O4: 87.6 | P4: =ROUND(N4*O4,-1) -> 610 | Q4: Ladder geral — nível 3/30
A5: 4 | B5: Errante | C5: Geral | D5: $ | E5: 1 | F5: 0.67414 | G5: 0.20517 | H5: 0.07828 | I5: 0.03069 | J5: 0.00876 | K5: 0.00297 | L5: 0 | M5: =SUM(F5:L5) -> 1.00001 | N5: =F5*Parâmetros!$B$4+G5*Parâmetros!$B$5+H5*Parâmetros!$B$6+I5*Parâmetros!$B$7+J5*Parâmetros!$B$8+K5*Parâmetros!$B$9+L5*Parâmetros!$B$10 -> 7.6477 | O5: 86.4 | P5: =ROUND(N5*O5,-1) -> 660 | Q5: Ladder geral — nível 4/30
A6: 5 | B6: Andarilho | C6: Geral | D6: $ | E6: 1 | F6: 0.66552 | G6: 0.2069 | H6: 0.08103 | I6: 0.03259 | J6: 0.01034 | K6: 0.00362 | L6: 0 | M6: =SUM(F6:L6) -> 1 | N6: =F6*Parâmetros!$B$4+G6*Parâmetros!$B$5+H6*Parâmetros!$B$6+I6*Parâmetros!$B$7+J6*Parâmetros!$B$8+K6*Parâmetros!$B$9+L6*Parâmetros!$B$10 -> 8.35596 | O6: 85.2 | P6: =ROUND(N6*O6,-1) -> 710 | Q6: Ladder geral — nível 5/30
A7: 6 | B7: Explorador | C7: Geral | D7: $ | E7: 1 | F7: 0.6569 | G7: 0.20862 | H7: 0.08379 | I7: 0.03448 | J7: 0.01193 | K7: 0.00428 | L7: 0 | M7: =SUM(F7:L7) -> 1 | N7: =F7*Parâmetros!$B$4+G7*Parâmetros!$B$5+H7*Parâmetros!$B$6+I7*Parâmetros!$B$7+J7*Parâmetros!$B$8+K7*Parâmetros!$B$9+L7*Parâmetros!$B$10 -> 9.07034 | O7: 84 | P7: =ROUND(N7*O7,-1) -> 760 | Q7: Ladder geral — nível 6/30
A8: 7 | B8: Caçador | C8: Geral | D8: $ | E8: 1 | F8: 0.64828 | G8: 0.21034 | H8: 0.08655 | I8: 0.03638 | J8: 0.01352 | K8: 0.00493 | L8: 0 | M8: =SUM(F8:L8) -> 1 | N8: =F8*Parâmetros!$B$4+G8*Parâmetros!$B$5+H8*Parâmetros!$B$6+I8*Parâmetros!$B$7+J8*Parâmetros!$B$8+K8*Parâmetros!$B$9+L8*Parâmetros!$B$10 -> 9.78022 | O8: 82.8 | P8: =ROUND(N8*O8,-1) -> 810 | Q8: Ladder geral — nível 7/30
A9: 8 | B9: Rastreador | C9: Geral | D9: $ | E9: 1 | F9: 0.63966 | G9: 0.21207 | H9: 0.08931 | I9: 0.03828 | J9: 0.0151 | K9: 0.00559 | L9: 0 | M9: =SUM(F9:L9) -> 1.00001 | N9: =F9*Parâmetros!$B$4+G9*Parâmetros!$B$5+H9*Parâmetros!$B$6+I9*Parâmetros!$B$7+J9*Parâmetros!$B$8+K9*Parâmetros!$B$9+L9*Parâmetros!$B$10 -> 10.49366 | O9: 81.6 | P9: =ROUND(N9*O9,-1) -> 860 | Q9: Ladder geral — nível 8/30
A10: 9 | B10: Guerreiro | C10: Geral | D10: $ | E10: 1 | F10: 0.63103 | G10: 0.21379 | H10: 0.09207 | I10: 0.04017 | J10: 0.01669 | K10: 0.00624 | L10: 0 | M10: =SUM(F10:L10) -> 0.99999 | N10: =F10*Parâmetros!$B$4+G10*Parâmetros!$B$5+H10*Parâmetros!$B$6+I10*Parâmetros!$B$7+J10*Parâmetros!$B$8+K10*Parâmetros!$B$9+L10*Parâmetros!$B$10 -> 11.20303 | O10: 80.3 | P10: =ROUND(N10*O10,-1) -> 900 | Q10: Ladder geral — nível 9/30
A11: 10 | B11: Bravo | C11: Geral | D11: $ | E11: 1 | F11: 0.62241 | G11: 0.21552 | H11: 0.09483 | I11: 0.04207 | J11: 0.01828 | K11: 0.0069 | L11: 0 | M11: =SUM(F11:L11) -> 1.00001 | N11: =F11*Parâmetros!$B$4+G11*Parâmetros!$B$5+H11*Parâmetros!$B$6+I11*Parâmetros!$B$7+J11*Parâmetros!$B$8+K11*Parâmetros!$B$9+L11*Parâmetros!$B$10 -> 11.91797 | O11: 79.1 | P11: =ROUND(N11*O11,-1) -> 940 | Q11: Ladder geral — nível 10/30
A12: 11 | B12: Guardião | C12: Geral | D12: $ | E12: 1 | F12: 0.61379 | G12: 0.21724 | H12: 0.09759 | I12: 0.04397 | J12: 0.01986 | K12: 0.00755 | L12: 0 | M12: =SUM(F12:L12) -> 1 | N12: =F12*Parâmetros!$B$4+G12*Parâmetros!$B$5+H12*Parâmetros!$B$6+I12*Parâmetros!$B$7+J12*Parâmetros!$B$8+K12*Parâmetros!$B$9+L12*Parâmetros!$B$10 -> 12.62635 | O12: 77.9 | P12: =ROUND(N12*O12,-1) -> 980 | Q12: Ladder geral — nível 11/30
A13: 12 | B13: Sentinela | C13: Geral | D13: $ | E13: 1 | F13: 0.60517 | G13: 0.21897 | H13: 0.10034 | I13: 0.04586 | J13: 0.02145 | K13: 0.00821 | L13: 0 | M13: =SUM(F13:L13) -> 1 | N13: =F13*Parâmetros!$B$4+G13*Parâmetros!$B$5+H13*Parâmetros!$B$6+I13*Parâmetros!$B$7+J13*Parâmetros!$B$8+K13*Parâmetros!$B$9+L13*Parâmetros!$B$10 -> 13.34061 | O13: 76.7 | P13: =ROUND(N13*O13,-1) -> 1020 | Q13: Ladder geral — nível 12/30
... A46: 45 | B46: Baú do Fundador | C46: Robux | D46: Robux | E46: 8 | F46: 0.1 | G46: 0.15 | H46: 0.2 | I46: 0.25 | J46: 0.2 | K46: 0.1 | L46: 0 | M46: =SUM(F46:L46) -> 1 | N46: =F46*Parâmetros!$B$4+G46*Parâmetros!$B$5+H46*Parâmetros!$B$6+I46*Parâmetros!$B$7+J46*Parâmetros!$B$8+K46*Parâmetros!$B$9+L46*Parâmetros!$B$10 -> 97.1 | O46: 30 | P46: =ROUND(N46*O46,-1) -> 2910 | Q46: Multi-carta (8 cartas por compra) — nível 9/9
A47: 46 | B47: Chegada | C47: Especial/Evento | D47: Grátis | E47: 1 | F47: 0.4 | G47: 0.3 | H47: 0.2 | I47: 0.08 | J47: 0.02 | K47: 0 | L47: 0 | M47: =SUM(F47:L47) -> 1 | N47: =F47*Parâmetros!$B$4+G47*Parâmetros!$B$5+H47*Parâmetros!$B$6+I47*Parâmetros!$B$7+J47*Parâmetros!$B$8+K47*Parâmetros!$B$9+L47*Parâmetros!$B$10 -> 12.8 | P47: Grátis | Q47: Starter — 1x por conta nova
A48: 47 | B48: Bênção Diária | C48: Especial/Evento | D48: Grátis | E48: 1 | F48: 0.8 | G48: 0.15 | H48: 0.04 | I48: 0.009 | J48: 0.001 | K48: 0 | L48: 0 | M48: =SUM(F48:L48) -> 1 | N48: =F48*Parâmetros!$B$4+G48*Parâmetros!$B$5+H48*Parâmetros!$B$6+I48*Parâmetros!$B$7+J48*Parâmetros!$B$8+K48*Parâmetros!$B$9+L48*Parâmetros!$B$10 -> 3.02 | P48: Grátis | Q48: Grátis, 1x por dia
A49: 48 | B49: Retorno do Herói | C49: Especial/Evento | D49: Grátis | E49: 1 | F49: 0.3 | G49: 0.3 | H49: 0.25 | I49: 0.1 | J49: 0.04 | K49: 0.01 | L49: 0 | M49: =SUM(F49:L49) -> 1 | N49: =F49*Parâmetros!$B$4+G49*Parâmetros!$B$5+H49*Parâmetros!$B$6+I49*Parâmetros!$B$7+J49*Parâmetros!$B$8+K49*Parâmetros!$B$9+L49*Parâmetros!$B$10 -> 22.6 | P49: Grátis | Q49: Reengajamento — condicional
A50: 49 | B50: Relâmpago | C50: Especial/Evento | D50: $ ou 💎 (a definir) | E50: 1 | F50: 0.55 | G50: 0.24 | H50: 0.12 | I50: 0.06 | J50: 0.025 | K50: 0.005 | L50: 0 | M50: =SUM(F50:L50) -> 1 | N50: =F50*Parâmetros!$B$4+G50*Parâmetros!$B$5+H50*Parâmetros!$B$6+I50*Parâmetros!$B$7+J50*Parâmetros!$B$8+K50*Parâmetros!$B$9+L50*Parâmetros!$B$10 -> 13.4 | P50: $ ou 💎 (a definir) | Q50: Venda-relâmpago — janela de tempo limitada, preço com desconto vs. equivalente
A51: 50 | B51: Sorte do Destino | C51: Especial/Evento | D51: $ ou 💎 (a definir) | E51: 1 | F51: 0.2 | G51: 0.2 | H51: 0.2 | I51: 0.2 | J51: 0.15 | K51: 0.05 | L51: 0 | M51: =SUM(F51:L51) -> 1 | N51: =F51*Parâmetros!$B$4+G51*Parâmetros!$B$5+H51*Parâmetros!$B$6+I51*Parâmetros!$B$7+J51*Parâmetros!$B$8+K51*Parâmetros!$B$9+L51*Parâmetros!$B$10 -> 62.5 | P51: $ ou 💎 (a definir) | Q51: Evento live — odds turbinadas temporariamente
A52: 51 | B52: Primeiro Renascimento | C52: Especial/Evento | D52: Grátis | E52: 1 | F52: 0.25 | G52: 0.25 | H52: 0.25 | I52: 0.15 | J52: 0.08 | K52: 0.02 | L52: 0 | M52: =SUM(F52:L52) -> 1 | N52: =F52*Parâmetros!$B$4+G52*Parâmetros!$B$5+H52*Parâmetros!$B$6+I52*Parâmetros!$B$7+J52*Parâmetros!$B$8+K52*Parâmetros!$B$9+L52*Parâmetros!$B$10 -> 35.75 | P52: Grátis | Q52: Dado automaticamente no 1º prestígio
A53: 52 | B53: Portal Divino | C53: Especial/Evento | D53: Evento (a definir) | E53: 1 | F53: 0 | G53: 0 | H53: 0 | I53: 0 | J53: 0 | K53: 0 | L53: 1 | M53: =SUM(F53:L53) -> 1 | N53: =F53*Parâmetros!$B$4+G53*Parâmetros!$B$5+H53*Parâmetros!$B$6+I53*Parâmetros!$B$7+J53*Parâmetros!$B$8+K53*Parâmetros!$B$9+L53*Parâmetros!$B$10 -> 10000 | P53: Evento (a definir) | Q53: ÚNICA fonte de Raridade Divino — garante 1 carta Divino (clã aleatório), sem fusão
A54: 53 | B54: Confluência Mística | C54: Especial/Evento | D54: $ ou 💎 (a definir) | E54: 3 | F54: 0.4 | G54: 0.25 | H54: 0.18 | I54: 0.1 | J54: 0.05 | K54: 0.02 | L54: 0 | M54: =SUM(F54:L54) -> 1 | N54: =F54*Parâmetros!$B$4+G54*Parâmetros!$B$5+H54*Parâmetros!$B$6+I54*Parâmetros!$B$7+J54*Parâmetros!$B$8+K54*Parâmetros!$B$9+L54*Parâmetros!$B$10 -> 27.64 | P54: $ ou 💎 (a definir) | Q54: Bundle — 3 cartas por compra
A55: 54 | B55: Aniversário | C55: Especial/Evento | D55: Grátis / Promo | E55: 1 | F55: 0.3 | G55: 0.25 | H55: 0.2 | I55: 0.15 | J55: 0.08 | K55: 0.02 | L55: 0 | M55: =SUM(F55:L55) -> 1 | N55: =F55*Parâmetros!$B$4+G55*Parâmetros!$B$5+H55*Parâmetros!$B$6+I55*Parâmetros!$B$7+J55*Parâmetros!$B$8+K55*Parâmetros!$B$9+L55*Parâmetros!$B$10 -> 34.9 | P55: Grátis | Q55: Evento anual — data de aniversário do jogo
A56: 55 | B56: Solstício de Verão | C56: Especial/Evento | D56: Promo (a definir) | E56: 1 | F56: 0.35 | G56: 0.28 | H56: 0.2 | I56: 0.12 | J56: 0.04 | K56: 0.01 | L56: 0 | M56: =SUM(F56:L56) -> 1 | N56: =F56*Parâmetros!$B$4+G56*Parâmetros!$B$5+H56*Parâmetros!$B$6+I56*Parâmetros!$B$7+J56*Parâmetros!$B$8+K56*Parâmetros!$B$9+L56*Parâmetros!$B$10 -> 22.63 | P56: Promo (a definir) | Q56: Sazonal — verão
A57: 56 | B57: Noite das Sombras | C57: Especial/Evento | D57: Promo (a definir) | E57: 1 | F57: 0.35 | G57: 0.27 | H57: 0.2 | I57: 0.12 | J57: 0.05 | K57: 0.01 | L57: 0 | M57: =SUM(F57:L57) -> 1 | N57: =F57*Parâmetros!$B$4+G57*Parâmetros!$B$5+H57*Parâmetros!$B$6+I57*Parâmetros!$B$7+J57*Parâmetros!$B$8+K57*Parâmetros!$B$9+L57*Parâmetros!$B$10 -> 24.07 | P57: Promo (a definir) | Q57: Sazonal — outubro
A58: 57 | B58: Amanhecer de Ano Novo | C58: Especial/Evento | D58: Promo (a definir) | E58: 1 | F58: 0.32 | G58: 0.28 | H58: 0.2 | I58: 0.13 | J58: 0.06 | K58: 0.01 | L58: 0 | M58: =SUM(F58:L58) -> 1 | N58: =F58*Parâmetros!$B$4+G58*Parâmetros!$B$5+H58*Parâmetros!$B$6+I58*Parâmetros!$B$7+J58*Parâmetros!$B$8+K58*Parâmetros!$B$9+L58*Parâmetros!$B$10 -> 26.1 | P58: Promo (a definir) | Q58: Sazonal — virada de ano
... A61: 60 | B61: Constância Semanal | C61: Especial/Evento | D61: Grátis | E61: 1 | F61: 0.3 | G61: 0.3 | H61: 0.22 | I61: 0.12 | J61: 0.05 | K61: 0.01 | L61: 0 | M61: =SUM(F61:L61) -> 1 | N61: =F61*Parâmetros!$B$4+G61*Parâmetros!$B$5+H61*Parâmetros!$B$6+I61*Parâmetros!$B$7+J61*Parâmetros!$B$8+K61*Parâmetros!$B$9+L61*Parâmetros!$B$10 -> 24.56 | P61: Grátis | Q61: Recompensa de streak semanal

Sheet Legenda
A1: Como usar esta planilha
A3: • Aba 'Parâmetros': multiplicador de valor por raridade (mesma fonte da aba Sistema de Raridade e Evolução do arquivo mestre). Editável.
A4: • Aba 'Catálogo de Pacotes': os 60 pacotes definidos, com odds (%) por raridade, EV (valor esperado em unidades de multiplicador), markup aplicado e preço calculado.
A5: • Células em AZUL = inputs editáveis (odds, cartas por compra, markup). Células em PRETO = fórmulas que recalculam automaticamente.
A6: • EV = soma de (odds da raridade × multiplicador da raridade). É um proxy do valor esperado de UMA carta desse pacote, não considera o valor-semente (seedValue) específico de cada criatura.
A7: • Preço = ROUND(EV × Markup, -1). O Markup é o quanto o pacote custa em relação ao EV — quanto maior, mais 'caro' o pacote é para o que ele entrega; a curva foi desenhada caindo (packs melhores custam relativamente menos por unidade de EV, incentivando gasto maior).
A8: • Pacotes de Especiais/Eventos com moeda 'a definir' ou 'Grátis' não têm markup/preço calculado — são decisões de monetização/liveops separadas.
A9: • Todos os pacotes sorteiam entre os 15 clãs de forma uniforme — a única fonte de Raridade Divino é o pacote 'Portal Divino' (evento).
A11: Pendências antes de implementar no PackCatalog.lua:
A12: - Validar se os preços em $ e 💎 fazem sentido frente à economia atual (EconomyService).
A13: - Definir preços reais em Robux (respeitar limites/mínimos do Roblox Developer Products).
A14: - Definir moeda e preço exatos dos pacotes de Especiais/Eventos marcados 'a definir'.
A15: - Rodar EV contra o seedValue médio real das 300 criaturas (não só o multiplicador de raridade) para achar o preço final em dinheiro do jogo/Robux.
